{
	"0" : 
	{
		"nbEvaluatedPrograms" : 35,
		"nbEvaluatedTeams" : 3,
		"nbExecutionForEachInstr" : 
		{
			"0" : 60,
			"1" : 34,
			"2" : 46,
			"3" : 43,
			"4" : 48
		},
		"traceTeamIds" : "0, 1, 9"
	},
	"1" : 
	{
		"nbEvaluatedPrograms" : 51,
		"nbEvaluatedTeams" : 4,
		"nbExecutionForEachInstr" : 
		{
			"0" : 62,
			"1" : 54,
			"2" : 71,
			"3" : 81,
			"4" : 73
		},
		"traceTeamIds" : "0, 4, 13, 23"
	},
	"10" : 
	{
		"nbEvaluatedPrograms" : 68,
		"nbEvaluatedTeams" : 6,
		"nbExecutionForEachInstr" : 
		{
			"0" : 118,
			"1" : 72,
			"2" : 97,
			"3" : 91,
			"4" : 91
		},
		"traceTeamIds" : "0, 1, 9, 21, 14, 29"
	},
	"100" : 
	{
		"nbEvaluatedPrograms" : 35,
		"nbEvaluatedTeams" : 3,
		"nbExecutionForEachInstr" : 
		{
			"0" : 60,
			"1" : 34,
			"2" : 46,
			"3" : 43,
			"4" : 48
		},
		"traceTeamIds" : "0, 1, 9"
	},
	"101" : 
	{
		"nbEvaluatedPrograms" : 85,
		"nbEvaluatedTeams" : 7,
		"nbExecutionForEachInstr" : 
		{
			"0" : 135,
			"1" : 97,
			"2" : 120,
			"3" : 115,
			"4" : 125
		},
		"traceTeamIds" : "0, 5, 23, 22, 14, 18, 15"
	},
	"102" : 
	{
		"nbEvaluatedPrograms" : 35,
		"nbEvaluatedTeams" : 3,
		"nbExecutionForEachInstr" : 
		{
			"0" : 49,
			"1" : 29,
			"2" : 53,
			"3" : 47,
			"4" : 57
		},
		"traceTeamIds" : "0, 5, 23"
	},
	"104" : 
	{
		"nbEvaluatedPrograms" : 71,
		"nbEvaluatedTeams" : 7,
		"nbExecutionForEachInstr" : 
		{
			"0" : 112,
			"1" : 78,
			"2" : 96,
			"3" : 97,
			"4" : 92
		},
		"traceTeamIds" : "0, 1, 9, 22, 14, 29, 7"
	},
	"105" : 
	{
		"nbEvaluatedPrograms" : 107,
		"nbEvaluatedTeams" : 9,
		"nbExecutionForEachInstr" : 
		{
			"0" : 185,
			"1" : 125,
			"2" : 157,
			"3" : 139,
			"4" : 159
		},
		"traceTeamIds" : "0, 5, 23, 6, 16, 19, 14, 18, 15"
	},
	"106" : 
	{
		"nbEvaluatedPrograms" : 37,
		"nbEvaluatedTeams" : 3,
		"nbExecutionForEachInstr" : 
		{
			"0" : 47,
			"1" : 42,
			"2" : 46,
			"3" : 56,
			"4" : 54
		},
		"traceTeamIds" : "0, 4, 9"
	},
	"11" : 
	{
		"nbEvaluatedPrograms" : 51,
		"nbEvaluatedTeams" : 4,
		"nbExecutionForEachInstr" : 
		{
			"0" : 62,
			"1" : 54,
			"2" : 71,
			"3" : 81,
			"4" : 73
		},
		"traceTeamIds" : "0, 4, 13, 23"
	},
	"111" : 
	{
		"nbEvaluatedPrograms" : 9,
		"nbEvaluatedTeams" : 1,
		"nbExecutionForEachInstr" : 
		{
			"0" : 9,
			"1" : 8,
			"2" : 10,
			"3" : 7,
			"4" : 11
		},
		"traceTeamIds" : "0"
	},
	"117" : 
	{
		"nbEvaluatedPrograms" : 107,
		"nbEvaluatedTeams" : 9,
		"nbExecutionForEachInstr" : 
		{
			"0" : 185,
			"1" : 125,
			"2" : 157,
			"3" : 139,
			"4" : 159
		},
		"traceTeamIds" : "0, 5, 23, 6, 16, 19, 14, 18, 15"
	},
	"118" : 
	{
		"nbEvaluatedPrograms" : 35,
		"nbEvaluatedTeams" : 3,
		"nbExecutionForEachInstr" : 
		{
			"0" : 49,
			"1" : 29,
			"2" : 53,
			"3" : 47,
			"4" : 57
		},
		"traceTeamIds" : "0, 5, 23"
	},
	"12" : 
	{
		"nbEvaluatedPrograms" : 35,
		"nbEvaluatedTeams" : 3,
		"nbExecutionForEachInstr" : 
		{
			"0" : 60,
			"1" : 34,
			"2" : 46,
			"3" : 43,
			"4" : 48
		},
		"traceTeamIds" : "0, 1, 9"
	},
	"121" : 
	{
		"nbEvaluatedPrograms" : 71,
		"nbEvaluatedTeams" : 7,
		"nbExecutionForEachInstr" : 
		{
			"0" : 112,
			"1" : 78,
			"2" : 96,
			"3" : 97,
			"4" : 92
		},
		"traceTeamIds" : "0, 1, 9, 22, 14, 29, 7"
	},
	"13" : 
	{
		"nbEvaluatedPrograms" : 35,
		"nbEvaluatedTeams" : 3,
		"nbExecutionForEachInstr" : 
		{
			"0" : 49,
			"1" : 29,
			"2" : 53,
			"3" : 47,
			"4" : 57
		},
		"traceTeamIds" : "0, 5, 23"
	},
	"130" : 
	{
		"nbEvaluatedPrograms" : 35,
		"nbEvaluatedTeams" : 4,
		"nbExecutionForEachInstr" : 
		{
			"0" : 43,
			"1" : 30,
			"2" : 55,
			"3" : 42,
			"4" : 65
		},
		"traceTeamIds" : "0, 5, 11, 30"
	},
	"133" : 
	{
		"nbEvaluatedPrograms" : 107,
		"nbEvaluatedTeams" : 9,
		"nbExecutionForEachInstr" : 
		{
			"0" : 185,
			"1" : 125,
			"2" : 157,
			"3" : 139,
			"4" : 159
		},
		"traceTeamIds" : "0, 5, 23, 6, 16, 19, 14, 18, 15"
	},
	"134" : 
	{
		"nbEvaluatedPrograms" : 107,
		"nbEvaluatedTeams" : 9,
		"nbExecutionForEachInstr" : 
		{
			"0" : 185,
			"1" : 125,
			"2" : 157,
			"3" : 139,
			"4" : 159
		},
		"traceTeamIds" : "0, 5, 23, 6, 16, 19, 14, 18, 15"
	},
	"136" : 
	{
		"nbEvaluatedPrograms" : 107,
		"nbEvaluatedTeams" : 9,
		"nbExecutionForEachInstr" : 
		{
			"0" : 185,
			"1" : 125,
			"2" : 157,
			"3" : 139,
			"4" : 159
		},
		"traceTeamIds" : "0, 5, 23, 6, 16, 19, 14, 18, 15"
	},
	"137" : 
	{
		"nbEvaluatedPrograms" : 107,
		"nbEvaluatedTeams" : 9,
		"nbExecutionForEachInstr" : 
		{
			"0" : 185,
			"1" : 125,
			"2" : 157,
			"3" : 139,
			"4" : 159
		},
		"traceTeamIds" : "0, 5, 23, 6, 16, 19, 14, 18, 15"
	},
	"14" : 
	{
		"nbEvaluatedPrograms" : 59,
		"nbEvaluatedTeams" : 5,
		"nbExecutionForEachInstr" : 
		{
			"0" : 92,
			"1" : 57,
			"2" : 91,
			"3" : 79,
			"4" : 92
		},
		"traceTeamIds" : "0, 5, 23, 6, 16"
	},
	"147" : 
	{
		"nbEvaluatedPrograms" : 71,
		"nbEvaluatedTeams" : 7,
		"nbExecutionForEachInstr" : 
		{
			"0" : 112,
			"1" : 78,
			"2" : 96,
			"3" : 97,
			"4" : 92
		},
		"traceTeamIds" : "0, 1, 9, 22, 14, 29, 7"
	},
	"15" : 
	{
		"nbEvaluatedPrograms" : 59,
		"nbEvaluatedTeams" : 5,
		"nbExecutionForEachInstr" : 
		{
			"0" : 92,
			"1" : 57,
			"2" : 91,
			"3" : 79,
			"4" : 92
		},
		"traceTeamIds" : "0, 5, 23, 6, 16"
	},
	"151" : 
	{
		"nbEvaluatedPrograms" : 35,
		"nbEvaluatedTeams" : 3,
		"nbExecutionForEachInstr" : 
		{
			"0" : 49,
			"1" : 29,
			"2" : 53,
			"3" : 47,
			"4" : 57
		},
		"traceTeamIds" : "0, 5, 23"
	},
	"152" : 
	{
		"nbEvaluatedPrograms" : 35,
		"nbEvaluatedTeams" : 4,
		"nbExecutionForEachInstr" : 
		{
			"0" : 43,
			"1" : 30,
			"2" : 55,
			"3" : 42,
			"4" : 65
		},
		"traceTeamIds" : "0, 5, 11, 30"
	},
	"157" : 
	{
		"nbEvaluatedPrograms" : 41,
		"nbEvaluatedTeams" : 4,
		"nbExecutionForEachInstr" : 
		{
			"0" : 56,
			"1" : 43,
			"2" : 59,
			"3" : 52,
			"4" : 70
		},
		"traceTeamIds" : "0, 5, 11, 18"
	},
	"16" : 
	{
		"nbEvaluatedPrograms" : 68,
		"nbEvaluatedTeams" : 6,
		"nbExecutionForEachInstr" : 
		{
			"0" : 118,
			"1" : 72,
			"2" : 97,
			"3" : 91,
			"4" : 91
		},
		"traceTeamIds" : "0, 1, 9, 21, 14, 29"
	},
	"164" : 
	{
		"nbEvaluatedPrograms" : 24,
		"nbEvaluatedTeams" : 2,
		"nbExecutionForEachInstr" : 
		{
			"0" : 24,
			"1" : 26,
			"2" : 27,
			"3" : 41,
			"4" : 34
		},
		"traceTeamIds" : "0, 4"
	},
	"167" : 
	{
		"nbEvaluatedPrograms" : 64,
		"nbEvaluatedTeams" : 5,
		"nbExecutionForEachInstr" : 
		{
			"0" : 116,
			"1" : 70,
			"2" : 93,
			"3" : 83,
			"4" : 90
		},
		"traceTeamIds" : "0, 1, 9, 21, 14"
	},
	"169" : 
	{
		"nbEvaluatedPrograms" : 107,
		"nbEvaluatedTeams" : 9,
		"nbExecutionForEachInstr" : 
		{
			"0" : 185,
			"1" : 125,
			"2" : 157,
			"3" : 139,
			"4" : 159
		},
		"traceTeamIds" : "0, 5, 23, 6, 16, 19, 14, 18, 15"
	},
	"17" : 
	{
		"nbEvaluatedPrograms" : 68,
		"nbEvaluatedTeams" : 6,
		"nbExecutionForEachInstr" : 
		{
			"0" : 110,
			"1" : 75,
			"2" : 93,
			"3" : 92,
			"4" : 90
		},
		"traceTeamIds" : "0, 1, 9, 22, 14, 29"
	},
	"170" : 
	{
		"nbEvaluatedPrograms" : 107,
		"nbEvaluatedTeams" : 9,
		"nbExecutionForEachInstr" : 
		{
			"0" : 185,
			"1" : 125,
			"2" : 157,
			"3" : 139,
			"4" : 159
		},
		"traceTeamIds" : "0, 5, 23, 6, 16, 19, 14, 18, 15"
	},
	"18" : 
	{
		"nbEvaluatedPrograms" : 59,
		"nbEvaluatedTeams" : 5,
		"nbExecutionForEachInstr" : 
		{
			"0" : 92,
			"1" : 57,
			"2" : 91,
			"3" : 79,
			"4" : 92
		},
		"traceTeamIds" : "0, 5, 23, 6, 16"
	},
	"19" : 
	{
		"nbEvaluatedPrograms" : 51,
		"nbEvaluatedTeams" : 4,
		"nbExecutionForEachInstr" : 
		{
			"0" : 62,
			"1" : 54,
			"2" : 71,
			"3" : 81,
			"4" : 73
		},
		"traceTeamIds" : "0, 4, 13, 23"
	},
	"191" : 
	{
		"nbEvaluatedPrograms" : 87,
		"nbEvaluatedTeams" : 7,
		"nbExecutionForEachInstr" : 
		{
			"0" : 151,
			"1" : 101,
			"2" : 118,
			"3" : 113,
			"4" : 121
		},
		"traceTeamIds" : "0, 1, 9, 22, 14, 33, 15"
	},
	"2" : 
	{
		"nbEvaluatedPrograms" : 59,
		"nbEvaluatedTeams" : 5,
		"nbExecutionForEachInstr" : 
		{
			"0" : 92,
			"1" : 57,
			"2" : 91,
			"3" : 79,
			"4" : 92
		},
		"traceTeamIds" : "0, 5, 23, 6, 16"
	},
	"20" : 
	{
		"nbEvaluatedPrograms" : 68,
		"nbEvaluatedTeams" : 6,
		"nbExecutionForEachInstr" : 
		{
			"0" : 110,
			"1" : 75,
			"2" : 93,
			"3" : 92,
			"4" : 90
		},
		"traceTeamIds" : "0, 1, 9, 22, 14, 29"
	},
	"21" : 
	{
		"nbEvaluatedPrograms" : 37,
		"nbEvaluatedTeams" : 3,
		"nbExecutionForEachInstr" : 
		{
			"0" : 47,
			"1" : 42,
			"2" : 46,
			"3" : 56,
			"4" : 54
		},
		"traceTeamIds" : "0, 4, 9"
	},
	"22" : 
	{
		"nbEvaluatedPrograms" : 59,
		"nbEvaluatedTeams" : 5,
		"nbExecutionForEachInstr" : 
		{
			"0" : 92,
			"1" : 57,
			"2" : 91,
			"3" : 79,
			"4" : 92
		},
		"traceTeamIds" : "0, 5, 23, 6, 16"
	},
	"23" : 
	{
		"nbEvaluatedPrograms" : 30,
		"nbEvaluatedTeams" : 3,
		"nbExecutionForEachInstr" : 
		{
			"0" : 38,
			"1" : 27,
			"2" : 46,
			"3" : 38,
			"4" : 57
		},
		"traceTeamIds" : "0, 5, 11"
	},
	"24" : 
	{
		"nbEvaluatedPrograms" : 64,
		"nbEvaluatedTeams" : 6,
		"nbExecutionForEachInstr" : 
		{
			"0" : 109,
			"1" : 77,
			"2" : 94,
			"3" : 80,
			"4" : 87
		},
		"traceTeamIds" : "0, 6, 16, 19, 14, 29"
	},
	"25" : 
	{
		"nbEvaluatedPrograms" : 85,
		"nbEvaluatedTeams" : 7,
		"nbExecutionForEachInstr" : 
		{
			"0" : 135,
			"1" : 97,
			"2" : 120,
			"3" : 115,
			"4" : 125
		},
		"traceTeamIds" : "0, 5, 23, 22, 14, 18, 15"
	},
	"26" : 
	{
		"nbEvaluatedPrograms" : 68,
		"nbEvaluatedTeams" : 6,
		"nbExecutionForEachInstr" : 
		{
			"0" : 110,
			"1" : 75,
			"2" : 93,
			"3" : 92,
			"4" : 90
		},
		"traceTeamIds" : "0, 1, 9, 22, 14, 29"
	},
	"27" : 
	{
		"nbEvaluatedPrograms" : 35,
		"nbEvaluatedTeams" : 3,
		"nbExecutionForEachInstr" : 
		{
			"0" : 49,
			"1" : 29,
			"2" : 53,
			"3" : 47,
			"4" : 57
		},
		"traceTeamIds" : "0, 5, 23"
	},
	"28" : 
	{
		"nbEvaluatedPrograms" : 68,
		"nbEvaluatedTeams" : 6,
		"nbExecutionForEachInstr" : 
		{
			"0" : 110,
			"1" : 75,
			"2" : 93,
			"3" : 92,
			"4" : 90
		},
		"traceTeamIds" : "0, 1, 9, 22, 14, 29"
	},
	"29" : 
	{
		"nbEvaluatedPrograms" : 68,
		"nbEvaluatedTeams" : 6,
		"nbExecutionForEachInstr" : 
		{
			"0" : 110,
			"1" : 75,
			"2" : 93,
			"3" : 92,
			"4" : 90
		},
		"traceTeamIds" : "0, 1, 9, 22, 14, 29"
	},
	"3" : 
	{
		"nbEvaluatedPrograms" : 68,
		"nbEvaluatedTeams" : 6,
		"nbExecutionForEachInstr" : 
		{
			"0" : 110,
			"1" : 75,
			"2" : 93,
			"3" : 92,
			"4" : 90
		},
		"traceTeamIds" : "0, 1, 9, 22, 14, 29"
	},
	"30" : 
	{
		"nbEvaluatedPrograms" : 59,
		"nbEvaluatedTeams" : 5,
		"nbExecutionForEachInstr" : 
		{
			"0" : 92,
			"1" : 57,
			"2" : 91,
			"3" : 79,
			"4" : 92
		},
		"traceTeamIds" : "0, 5, 23, 6, 16"
	},
	"31" : 
	{
		"nbEvaluatedPrograms" : 41,
		"nbEvaluatedTeams" : 4,
		"nbExecutionForEachInstr" : 
		{
			"0" : 56,
			"1" : 43,
			"2" : 59,
			"3" : 52,
			"4" : 70
		},
		"traceTeamIds" : "0, 5, 11, 18"
	},
	"32" : 
	{
		"nbEvaluatedPrograms" : 68,
		"nbEvaluatedTeams" : 6,
		"nbExecutionForEachInstr" : 
		{
			"0" : 110,
			"1" : 75,
			"2" : 93,
			"3" : 92,
			"4" : 90
		},
		"traceTeamIds" : "0, 1, 9, 22, 14, 29"
	},
	"33" : 
	{
		"nbEvaluatedPrograms" : 35,
		"nbEvaluatedTeams" : 3,
		"nbExecutionForEachInstr" : 
		{
			"0" : 60,
			"1" : 34,
			"2" : 46,
			"3" : 43,
			"4" : 48
		},
		"traceTeamIds" : "0, 1, 9"
	},
	"34" : 
	{
		"nbEvaluatedPrograms" : 68,
		"nbEvaluatedTeams" : 6,
		"nbExecutionForEachInstr" : 
		{
			"0" : 110,
			"1" : 75,
			"2" : 93,
			"3" : 92,
			"4" : 90
		},
		"traceTeamIds" : "0, 1, 9, 22, 14, 29"
	},
	"35" : 
	{
		"nbEvaluatedPrograms" : 68,
		"nbEvaluatedTeams" : 6,
		"nbExecutionForEachInstr" : 
		{
			"0" : 118,
			"1" : 72,
			"2" : 97,
			"3" : 91,
			"4" : 91
		},
		"traceTeamIds" : "0, 1, 9, 21, 14, 29"
	},
	"36" : 
	{
		"nbEvaluatedPrograms" : 107,
		"nbEvaluatedTeams" : 9,
		"nbExecutionForEachInstr" : 
		{
			"0" : 185,
			"1" : 125,
			"2" : 157,
			"3" : 139,
			"4" : 159
		},
		"traceTeamIds" : "0, 5, 23, 6, 16, 19, 14, 18, 15"
	},
	"37" : 
	{
		"nbEvaluatedPrograms" : 37,
		"nbEvaluatedTeams" : 3,
		"nbExecutionForEachInstr" : 
		{
			"0" : 47,
			"1" : 42,
			"2" : 46,
			"3" : 56,
			"4" : 54
		},
		"traceTeamIds" : "0, 4, 9"
	},
	"38" : 
	{
		"nbEvaluatedPrograms" : 37,
		"nbEvaluatedTeams" : 3,
		"nbExecutionForEachInstr" : 
		{
			"0" : 47,
			"1" : 42,
			"2" : 46,
			"3" : 56,
			"4" : 54
		},
		"traceTeamIds" : "0, 4, 9"
	},
	"39" : 
	{
		"nbEvaluatedPrograms" : 68,
		"nbEvaluatedTeams" : 6,
		"nbExecutionForEachInstr" : 
		{
			"0" : 110,
			"1" : 75,
			"2" : 93,
			"3" : 92,
			"4" : 90
		},
		"traceTeamIds" : "0, 1, 9, 22, 14, 29"
	},
	"4" : 
	{
		"nbEvaluatedPrograms" : 33,
		"nbEvaluatedTeams" : 3,
		"nbExecutionForEachInstr" : 
		{
			"0" : 52,
			"1" : 36,
			"2" : 48,
			"3" : 39,
			"4" : 46
		},
		"traceTeamIds" : "0, 6, 16"
	},
	"40" : 
	{
		"nbEvaluatedPrograms" : 37,
		"nbEvaluatedTeams" : 3,
		"nbExecutionForEachInstr" : 
		{
			"0" : 47,
			"1" : 42,
			"2" : 46,
			"3" : 56,
			"4" : 54
		},
		"traceTeamIds" : "0, 4, 9"
	},
	"41" : 
	{
		"nbEvaluatedPrograms" : 37,
		"nbEvaluatedTeams" : 3,
		"nbExecutionForEachInstr" : 
		{
			"0" : 47,
			"1" : 42,
			"2" : 46,
			"3" : 56,
			"4" : 54
		},
		"traceTeamIds" : "0, 4, 9"
	},
	"42" : 
	{
		"nbEvaluatedPrograms" : 68,
		"nbEvaluatedTeams" : 6,
		"nbExecutionForEachInstr" : 
		{
			"0" : 118,
			"1" : 72,
			"2" : 97,
			"3" : 91,
			"4" : 91
		},
		"traceTeamIds" : "0, 1, 9, 21, 14, 29"
	},
	"43" : 
	{
		"nbEvaluatedPrograms" : 85,
		"nbEvaluatedTeams" : 7,
		"nbExecutionForEachInstr" : 
		{
			"0" : 135,
			"1" : 97,
			"2" : 120,
			"3" : 115,
			"4" : 125
		},
		"traceTeamIds" : "0, 5, 23, 22, 14, 18, 15"
	},
	"44" : 
	{
		"nbEvaluatedPrograms" : 85,
		"nbEvaluatedTeams" : 7,
		"nbExecutionForEachInstr" : 
		{
			"0" : 135,
			"1" : 97,
			"2" : 120,
			"3" : 115,
			"4" : 125
		},
		"traceTeamIds" : "0, 5, 23, 22, 14, 18, 15"
	},
	"45" : 
	{
		"nbEvaluatedPrograms" : 51,
		"nbEvaluatedTeams" : 4,
		"nbExecutionForEachInstr" : 
		{
			"0" : 62,
			"1" : 54,
			"2" : 71,
			"3" : 81,
			"4" : 73
		},
		"traceTeamIds" : "0, 4, 13, 23"
	},
	"46" : 
	{
		"nbEvaluatedPrograms" : 51,
		"nbEvaluatedTeams" : 4,
		"nbExecutionForEachInstr" : 
		{
			"0" : 62,
			"1" : 54,
			"2" : 71,
			"3" : 81,
			"4" : 73
		},
		"traceTeamIds" : "0, 4, 13, 23"
	},
	"47" : 
	{
		"nbEvaluatedPrograms" : 71,
		"nbEvaluatedTeams" : 7,
		"nbExecutionForEachInstr" : 
		{
			"0" : 112,
			"1" : 78,
			"2" : 96,
			"3" : 97,
			"4" : 92
		},
		"traceTeamIds" : "0, 1, 9, 22, 14, 29, 7"
	},
	"48" : 
	{
		"nbEvaluatedPrograms" : 85,
		"nbEvaluatedTeams" : 7,
		"nbExecutionForEachInstr" : 
		{
			"0" : 135,
			"1" : 97,
			"2" : 120,
			"3" : 115,
			"4" : 125
		},
		"traceTeamIds" : "0, 5, 23, 22, 14, 18, 15"
	},
	"49" : 
	{
		"nbEvaluatedPrograms" : 68,
		"nbEvaluatedTeams" : 6,
		"nbExecutionForEachInstr" : 
		{
			"0" : 110,
			"1" : 75,
			"2" : 93,
			"3" : 92,
			"4" : 90
		},
		"traceTeamIds" : "0, 1, 9, 22, 14, 29"
	},
	"5" : 
	{
		"nbEvaluatedPrograms" : 51,
		"nbEvaluatedTeams" : 4,
		"nbExecutionForEachInstr" : 
		{
			"0" : 62,
			"1" : 54,
			"2" : 71,
			"3" : 81,
			"4" : 73
		},
		"traceTeamIds" : "0, 4, 13, 23"
	},
	"50" : 
	{
		"nbEvaluatedPrograms" : 85,
		"nbEvaluatedTeams" : 7,
		"nbExecutionForEachInstr" : 
		{
			"0" : 135,
			"1" : 97,
			"2" : 120,
			"3" : 115,
			"4" : 125
		},
		"traceTeamIds" : "0, 5, 23, 22, 14, 18, 15"
	},
	"52" : 
	{
		"nbEvaluatedPrograms" : 51,
		"nbEvaluatedTeams" : 4,
		"nbExecutionForEachInstr" : 
		{
			"0" : 62,
			"1" : 54,
			"2" : 71,
			"3" : 81,
			"4" : 73
		},
		"traceTeamIds" : "0, 4, 13, 23"
	},
	"53" : 
	{
		"nbEvaluatedPrograms" : 35,
		"nbEvaluatedTeams" : 3,
		"nbExecutionForEachInstr" : 
		{
			"0" : 60,
			"1" : 34,
			"2" : 46,
			"3" : 43,
			"4" : 48
		},
		"traceTeamIds" : "0, 1, 9"
	},
	"54" : 
	{
		"nbEvaluatedPrograms" : 85,
		"nbEvaluatedTeams" : 7,
		"nbExecutionForEachInstr" : 
		{
			"0" : 135,
			"1" : 97,
			"2" : 120,
			"3" : 115,
			"4" : 125
		},
		"traceTeamIds" : "0, 5, 23, 22, 14, 18, 15"
	},
	"55" : 
	{
		"nbEvaluatedPrograms" : 87,
		"nbEvaluatedTeams" : 7,
		"nbExecutionForEachInstr" : 
		{
			"0" : 151,
			"1" : 101,
			"2" : 118,
			"3" : 113,
			"4" : 121
		},
		"traceTeamIds" : "0, 1, 9, 22, 14, 33, 15"
	},
	"58" : 
	{
		"nbEvaluatedPrograms" : 68,
		"nbEvaluatedTeams" : 6,
		"nbExecutionForEachInstr" : 
		{
			"0" : 118,
			"1" : 72,
			"2" : 97,
			"3" : 91,
			"4" : 91
		},
		"traceTeamIds" : "0, 1, 9, 21, 14, 29"
	},
	"59" : 
	{
		"nbEvaluatedPrograms" : 35,
		"nbEvaluatedTeams" : 3,
		"nbExecutionForEachInstr" : 
		{
			"0" : 60,
			"1" : 34,
			"2" : 46,
			"3" : 43,
			"4" : 48
		},
		"traceTeamIds" : "0, 1, 9"
	},
	"6" : 
	{
		"nbEvaluatedPrograms" : 68,
		"nbEvaluatedTeams" : 6,
		"nbExecutionForEachInstr" : 
		{
			"0" : 118,
			"1" : 72,
			"2" : 97,
			"3" : 91,
			"4" : 91
		},
		"traceTeamIds" : "0, 1, 9, 21, 14, 29"
	},
	"62" : 
	{
		"nbEvaluatedPrograms" : 59,
		"nbEvaluatedTeams" : 5,
		"nbExecutionForEachInstr" : 
		{
			"0" : 92,
			"1" : 57,
			"2" : 91,
			"3" : 79,
			"4" : 92
		},
		"traceTeamIds" : "0, 5, 23, 6, 16"
	},
	"63" : 
	{
		"nbEvaluatedPrograms" : 59,
		"nbEvaluatedTeams" : 5,
		"nbExecutionForEachInstr" : 
		{
			"0" : 92,
			"1" : 57,
			"2" : 91,
			"3" : 79,
			"4" : 92
		},
		"traceTeamIds" : "0, 5, 23, 6, 16"
	},
	"64" : 
	{
		"nbEvaluatedPrograms" : 35,
		"nbEvaluatedTeams" : 3,
		"nbExecutionForEachInstr" : 
		{
			"0" : 60,
			"1" : 34,
			"2" : 46,
			"3" : 43,
			"4" : 48
		},
		"traceTeamIds" : "0, 1, 9"
	},
	"65" : 
	{
		"nbEvaluatedPrograms" : 37,
		"nbEvaluatedTeams" : 3,
		"nbExecutionForEachInstr" : 
		{
			"0" : 47,
			"1" : 42,
			"2" : 46,
			"3" : 56,
			"4" : 54
		},
		"traceTeamIds" : "0, 4, 9"
	},
	"66" : 
	{
		"nbEvaluatedPrograms" : 59,
		"nbEvaluatedTeams" : 5,
		"nbExecutionForEachInstr" : 
		{
			"0" : 92,
			"1" : 57,
			"2" : 91,
			"3" : 79,
			"4" : 92
		},
		"traceTeamIds" : "0, 5, 23, 6, 16"
	},
	"68" : 
	{
		"nbEvaluatedPrograms" : 54,
		"nbEvaluatedTeams" : 6,
		"nbExecutionForEachInstr" : 
		{
			"0" : 78,
			"1" : 59,
			"2" : 73,
			"3" : 70,
			"4" : 86
		},
		"traceTeamIds" : "0, 5, 11, 18, 15, 7"
	},
	"69" : 
	{
		"nbEvaluatedPrograms" : 68,
		"nbEvaluatedTeams" : 6,
		"nbExecutionForEachInstr" : 
		{
			"0" : 118,
			"1" : 72,
			"2" : 97,
			"3" : 91,
			"4" : 91
		},
		"traceTeamIds" : "0, 1, 9, 21, 14, 29"
	},
	"7" : 
	{
		"nbEvaluatedPrograms" : 85,
		"nbEvaluatedTeams" : 7,
		"nbExecutionForEachInstr" : 
		{
			"0" : 135,
			"1" : 97,
			"2" : 120,
			"3" : 115,
			"4" : 125
		},
		"traceTeamIds" : "0, 5, 23, 22, 14, 18, 15"
	},
	"73" : 
	{
		"nbEvaluatedPrograms" : 35,
		"nbEvaluatedTeams" : 3,
		"nbExecutionForEachInstr" : 
		{
			"0" : 60,
			"1" : 34,
			"2" : 46,
			"3" : 43,
			"4" : 48
		},
		"traceTeamIds" : "0, 1, 9"
	},
	"75" : 
	{
		"nbEvaluatedPrograms" : 85,
		"nbEvaluatedTeams" : 7,
		"nbExecutionForEachInstr" : 
		{
			"0" : 135,
			"1" : 97,
			"2" : 120,
			"3" : 115,
			"4" : 125
		},
		"traceTeamIds" : "0, 5, 23, 22, 14, 18, 15"
	},
	"76" : 
	{
		"nbEvaluatedPrograms" : 37,
		"nbEvaluatedTeams" : 3,
		"nbExecutionForEachInstr" : 
		{
			"0" : 47,
			"1" : 42,
			"2" : 46,
			"3" : 56,
			"4" : 54
		},
		"traceTeamIds" : "0, 4, 9"
	},
	"78" : 
	{
		"nbEvaluatedPrograms" : 68,
		"nbEvaluatedTeams" : 6,
		"nbExecutionForEachInstr" : 
		{
			"0" : 118,
			"1" : 72,
			"2" : 97,
			"3" : 91,
			"4" : 91
		},
		"traceTeamIds" : "0, 1, 9, 21, 14, 29"
	},
	"8" : 
	{
		"nbEvaluatedPrograms" : 51,
		"nbEvaluatedTeams" : 4,
		"nbExecutionForEachInstr" : 
		{
			"0" : 62,
			"1" : 54,
			"2" : 71,
			"3" : 81,
			"4" : 73
		},
		"traceTeamIds" : "0, 4, 13, 23"
	},
	"83" : 
	{
		"nbEvaluatedPrograms" : 71,
		"nbEvaluatedTeams" : 7,
		"nbExecutionForEachInstr" : 
		{
			"0" : 112,
			"1" : 78,
			"2" : 96,
			"3" : 97,
			"4" : 92
		},
		"traceTeamIds" : "0, 1, 9, 22, 14, 29, 7"
	},
	"84" : 
	{
		"nbEvaluatedPrograms" : 37,
		"nbEvaluatedTeams" : 3,
		"nbExecutionForEachInstr" : 
		{
			"0" : 47,
			"1" : 42,
			"2" : 46,
			"3" : 56,
			"4" : 54
		},
		"traceTeamIds" : "0, 4, 9"
	},
	"86" : 
	{
		"nbEvaluatedPrograms" : 107,
		"nbEvaluatedTeams" : 9,
		"nbExecutionForEachInstr" : 
		{
			"0" : 185,
			"1" : 125,
			"2" : 157,
			"3" : 139,
			"4" : 159
		},
		"traceTeamIds" : "0, 5, 23, 6, 16, 19, 14, 18, 15"
	},
	"88" : 
	{
		"nbEvaluatedPrograms" : 37,
		"nbEvaluatedTeams" : 3,
		"nbExecutionForEachInstr" : 
		{
			"0" : 47,
			"1" : 42,
			"2" : 46,
			"3" : 56,
			"4" : 54
		},
		"traceTeamIds" : "0, 4, 9"
	},
	"9" : 
	{
		"nbEvaluatedPrograms" : 59,
		"nbEvaluatedTeams" : 5,
		"nbExecutionForEachInstr" : 
		{
			"0" : 92,
			"1" : 57,
			"2" : 91,
			"3" : 79,
			"4" : 92
		},
		"traceTeamIds" : "0, 5, 23, 6, 16"
	},
	"90" : 
	{
		"nbEvaluatedPrograms" : 24,
		"nbEvaluatedTeams" : 2,
		"nbExecutionForEachInstr" : 
		{
			"0" : 24,
			"1" : 26,
			"2" : 27,
			"3" : 41,
			"4" : 34
		},
		"traceTeamIds" : "0, 4"
	},
	"95" : 
	{
		"nbEvaluatedPrograms" : 35,
		"nbEvaluatedTeams" : 4,
		"nbExecutionForEachInstr" : 
		{
			"0" : 43,
			"1" : 30,
			"2" : 55,
			"3" : 42,
			"4" : 65
		},
		"traceTeamIds" : "0, 5, 11, 30"
	},
	"98" : 
	{
		"nbEvaluatedPrograms" : 35,
		"nbEvaluatedTeams" : 3,
		"nbExecutionForEachInstr" : 
		{
			"0" : 60,
			"1" : 34,
			"2" : 46,
			"3" : 43,
			"4" : 48
		},
		"traceTeamIds" : "0, 1, 9"
	},
	"99" : 
	{
		"nbEvaluatedPrograms" : 35,
		"nbEvaluatedTeams" : 3,
		"nbExecutionForEachInstr" : 
		{
			"0" : 60,
			"1" : 34,
			"2" : 46,
			"3" : 43,
			"4" : 48
		},
		"traceTeamIds" : "0, 1, 9"
	}
}