{
	"0" : 
	{
		"nbEvaluatedPrograms" : 23,
		"nbEvaluatedTeams" : 6,
		"nbExecutionForEachInstr" : 
		{
			"0" : 9,
			"1" : 5,
			"2" : 3,
			"3" : 2,
			"4" : 7,
			"5" : 1
		},
		"traceTeamIds" : "0, 1, 6, 5, 13, 7"
	},
	"1" : 
	{
		"nbEvaluatedPrograms" : 20,
		"nbEvaluatedTeams" : 7,
		"nbExecutionForEachInstr" : 
		{
			"0" : 5,
			"1" : 4,
			"2" : 4,
			"3" : 3,
			"4" : 2,
			"5" : 1,
			"6" : 1
		},
		"traceTeamIds" : "0, 4, 11, 22, 30, 17, 24"
	},
	"10" : 
	{
		"nbEvaluatedPrograms" : 21,
		"nbEvaluatedTeams" : 6,
		"nbExecutionForEachInstr" : 
		{
			"0" : 8,
			"1" : 4,
			"2" : 3,
			"3" : 2,
			"4" : 4,
			"5" : 2
		},
		"traceTeamIds" : "0, 1, 6, 16, 27, 26"
	},
	"100" : 
	{
		"nbEvaluatedPrograms" : 29,
		"nbEvaluatedTeams" : 8,
		"nbExecutionForEachInstr" : 
		{
			"0" : 10,
			"1" : 7,
			"2" : 3,
			"3" : 3,
			"4" : 7,
			"5" : 2
		},
		"traceTeamIds" : "0, 1, 6, 5, 13, 7, 17, 24"
	},
	"101" : 
	{
		"nbEvaluatedPrograms" : 22,
		"nbEvaluatedTeams" : 4,
		"nbExecutionForEachInstr" : 
		{
			"0" : 9,
			"1" : 6,
			"2" : 3,
			"3" : 2,
			"4" : 3,
			"5" : 1
		},
		"traceTeamIds" : "0, 2, 8, 7"
	},
	"102" : 
	{
		"nbEvaluatedPrograms" : 19,
		"nbEvaluatedTeams" : 7,
		"nbExecutionForEachInstr" : 
		{
			"0" : 3,
			"1" : 5,
			"2" : 3,
			"3" : 4,
			"4" : 3,
			"5" : 2
		},
		"traceTeamIds" : "0, 4, 11, 23, 7, 17, 24"
	},
	"104" : 
	{
		"nbEvaluatedPrograms" : 26,
		"nbEvaluatedTeams" : 6,
		"nbExecutionForEachInstr" : 
		{
			"0" : 11,
			"1" : 7,
			"2" : 3,
			"4" : 5
		},
		"traceTeamIds" : "0, 2, 8, 5, 12, 24"
	},
	"105" : 
	{
		"nbEvaluatedPrograms" : 27,
		"nbEvaluatedTeams" : 6,
		"nbExecutionForEachInstr" : 
		{
			"0" : 9,
			"1" : 8,
			"2" : 4,
			"3" : 1,
			"4" : 3,
			"5" : 3
		},
		"traceTeamIds" : "0, 2, 8, 15, 20, 28"
	},
	"106" : 
	{
		"nbEvaluatedPrograms" : 23,
		"nbEvaluatedTeams" : 6,
		"nbExecutionForEachInstr" : 
		{
			"0" : 7,
			"1" : 5,
			"2" : 6,
			"3" : 1,
			"4" : 1,
			"5" : 3
		},
		"traceTeamIds" : "0, 3, 10, 15, 20, 28"
	},
	"108" : 
	{
		"nbEvaluatedPrograms" : 29,
		"nbEvaluatedTeams" : 6,
		"nbExecutionForEachInstr" : 
		{
			"0" : 10,
			"1" : 8,
			"2" : 4,
			"3" : 3,
			"4" : 4,
			"5" : 2
		},
		"traceTeamIds" : "0, 2, 8, 15, 7, 17"
	},
	"109" : 
	{
		"nbEvaluatedPrograms" : 18,
		"nbEvaluatedTeams" : 5,
		"nbExecutionForEachInstr" : 
		{
			"0" : 6,
			"1" : 4,
			"2" : 3,
			"3" : 2,
			"4" : 4,
			"5" : 1
		},
		"traceTeamIds" : "0, 3, 5, 13, 7"
	},
	"11" : 
	{
		"nbEvaluatedPrograms" : 29,
		"nbEvaluatedTeams" : 8,
		"nbExecutionForEachInstr" : 
		{
			"0" : 10,
			"1" : 7,
			"2" : 3,
			"3" : 3,
			"4" : 7,
			"5" : 2
		},
		"traceTeamIds" : "0, 1, 6, 5, 13, 7, 17, 24"
	},
	"110" : 
	{
		"nbEvaluatedPrograms" : 18,
		"nbEvaluatedTeams" : 5,
		"nbExecutionForEachInstr" : 
		{
			"0" : 5,
			"1" : 3,
			"2" : 3,
			"3" : 3,
			"4" : 2,
			"5" : 2
		},
		"traceTeamIds" : "0, 3, 7, 19, 26"
	},
	"111" : 
	{
		"nbEvaluatedPrograms" : 26,
		"nbEvaluatedTeams" : 6,
		"nbExecutionForEachInstr" : 
		{
			"0" : 9,
			"1" : 6,
			"2" : 3,
			"3" : 3,
			"4" : 4,
			"5" : 2
		},
		"traceTeamIds" : "0, 2, 8, 7, 19, 26"
	},
	"112" : 
	{
		"nbEvaluatedPrograms" : 29,
		"nbEvaluatedTeams" : 6,
		"nbExecutionForEachInstr" : 
		{
			"0" : 10,
			"1" : 8,
			"2" : 4,
			"3" : 3,
			"4" : 4,
			"5" : 2
		},
		"traceTeamIds" : "0, 2, 8, 15, 7, 17"
	},
	"113" : 
	{
		"nbEvaluatedPrograms" : 26,
		"nbEvaluatedTeams" : 6,
		"nbExecutionForEachInstr" : 
		{
			"0" : 10,
			"1" : 7,
			"2" : 3,
			"3" : 2,
			"4" : 6,
			"5" : 1
		},
		"traceTeamIds" : "0, 2, 8, 5, 13, 7"
	},
	"114" : 
	{
		"nbEvaluatedPrograms" : 17,
		"nbEvaluatedTeams" : 6,
		"nbExecutionForEachInstr" : 
		{
			"0" : 3,
			"1" : 4,
			"2" : 3,
			"3" : 4,
			"4" : 3,
			"5" : 2
		},
		"traceTeamIds" : "0, 4, 11, 23, 7, 17"
	},
	"115" : 
	{
		"nbEvaluatedPrograms" : 15,
		"nbEvaluatedTeams" : 5,
		"nbExecutionForEachInstr" : 
		{
			"0" : 4,
			"1" : 3,
			"2" : 4,
			"3" : 3,
			"4" : 1,
			"5" : 1
		},
		"traceTeamIds" : "0, 4, 11, 22, 20"
	},
	"116" : 
	{
		"nbEvaluatedPrograms" : 32,
		"nbEvaluatedTeams" : 8,
		"nbExecutionForEachInstr" : 
		{
			"0" : 11,
			"1" : 9,
			"2" : 3,
			"3" : 3,
			"4" : 6,
			"5" : 2
		},
		"traceTeamIds" : "0, 2, 8, 5, 13, 7, 17, 24"
	},
	"118" : 
	{
		"nbEvaluatedPrograms" : 30,
		"nbEvaluatedTeams" : 7,
		"nbExecutionForEachInstr" : 
		{
			"0" : 12,
			"1" : 8,
			"2" : 3,
			"3" : 1,
			"4" : 5,
			"5" : 1
		},
		"traceTeamIds" : "0, 2, 8, 5, 12, 17, 24"
	},
	"12" : 
	{
		"nbEvaluatedPrograms" : 23,
		"nbEvaluatedTeams" : 6,
		"nbExecutionForEachInstr" : 
		{
			"0" : 9,
			"1" : 5,
			"2" : 3,
			"3" : 2,
			"4" : 7,
			"5" : 1
		},
		"traceTeamIds" : "0, 1, 6, 5, 13, 7"
	},
	"120" : 
	{
		"nbEvaluatedPrograms" : 17,
		"nbEvaluatedTeams" : 6,
		"nbExecutionForEachInstr" : 
		{
			"0" : 3,
			"1" : 4,
			"2" : 3,
			"3" : 4,
			"4" : 3,
			"5" : 2
		},
		"traceTeamIds" : "0, 4, 11, 23, 7, 17"
	},
	"121" : 
	{
		"nbEvaluatedPrograms" : 21,
		"nbEvaluatedTeams" : 5,
		"nbExecutionForEachInstr" : 
		{
			"0" : 10,
			"1" : 4,
			"2" : 3,
			"4" : 6
		},
		"traceTeamIds" : "0, 1, 6, 5, 12"
	},
	"122" : 
	{
		"nbEvaluatedPrograms" : 26,
		"nbEvaluatedTeams" : 6,
		"nbExecutionForEachInstr" : 
		{
			"0" : 10,
			"1" : 7,
			"2" : 3,
			"3" : 2,
			"4" : 6,
			"5" : 1
		},
		"traceTeamIds" : "0, 2, 8, 5, 13, 7"
	},
	"123" : 
	{
		"nbEvaluatedPrograms" : 18,
		"nbEvaluatedTeams" : 5,
		"nbExecutionForEachInstr" : 
		{
			"0" : 5,
			"1" : 3,
			"2" : 3,
			"3" : 3,
			"4" : 2,
			"5" : 2
		},
		"traceTeamIds" : "0, 3, 7, 19, 26"
	},
	"124" : 
	{
		"nbEvaluatedPrograms" : 23,
		"nbEvaluatedTeams" : 6,
		"nbExecutionForEachInstr" : 
		{
			"0" : 9,
			"1" : 5,
			"2" : 3,
			"3" : 2,
			"4" : 7,
			"5" : 1
		},
		"traceTeamIds" : "0, 1, 6, 5, 13, 7"
	},
	"125" : 
	{
		"nbEvaluatedPrograms" : 25,
		"nbEvaluatedTeams" : 6,
		"nbExecutionForEachInstr" : 
		{
			"0" : 11,
			"1" : 5,
			"2" : 3,
			"3" : 1,
			"4" : 6,
			"5" : 1
		},
		"traceTeamIds" : "0, 1, 6, 5, 12, 17"
	},
	"126" : 
	{
		"nbEvaluatedPrograms" : 21,
		"nbEvaluatedTeams" : 5,
		"nbExecutionForEachInstr" : 
		{
			"0" : 7,
			"1" : 4,
			"2" : 6,
			"3" : 2,
			"4" : 2,
			"5" : 1
		},
		"traceTeamIds" : "0, 3, 10, 15, 7"
	},
	"127" : 
	{
		"nbEvaluatedPrograms" : 19,
		"nbEvaluatedTeams" : 7,
		"nbExecutionForEachInstr" : 
		{
			"0" : 3,
			"1" : 5,
			"2" : 3,
			"3" : 4,
			"4" : 3,
			"5" : 2
		},
		"traceTeamIds" : "0, 4, 11, 23, 7, 17, 24"
	},
	"128" : 
	{
		"nbEvaluatedPrograms" : 15,
		"nbEvaluatedTeams" : 5,
		"nbExecutionForEachInstr" : 
		{
			"0" : 4,
			"1" : 3,
			"2" : 4,
			"3" : 3,
			"4" : 1,
			"5" : 1
		},
		"traceTeamIds" : "0, 4, 11, 22, 20"
	},
	"129" : 
	{
		"nbEvaluatedPrograms" : 29,
		"nbEvaluatedTeams" : 7,
		"nbExecutionForEachInstr" : 
		{
			"0" : 9,
			"1" : 7,
			"2" : 4,
			"3" : 3,
			"4" : 5,
			"5" : 2
		},
		"traceTeamIds" : "0, 2, 8, 15, 7, 19, 26"
	},
	"13" : 
	{
		"nbEvaluatedPrograms" : 19,
		"nbEvaluatedTeams" : 7,
		"nbExecutionForEachInstr" : 
		{
			"0" : 3,
			"1" : 5,
			"2" : 3,
			"3" : 4,
			"4" : 3,
			"5" : 2
		},
		"traceTeamIds" : "0, 4, 11, 23, 7, 17, 24"
	},
	"130" : 
	{
		"nbEvaluatedPrograms" : 19,
		"nbEvaluatedTeams" : 7,
		"nbExecutionForEachInstr" : 
		{
			"0" : 3,
			"1" : 5,
			"2" : 3,
			"3" : 4,
			"4" : 3,
			"5" : 2
		},
		"traceTeamIds" : "0, 4, 11, 23, 7, 17, 24"
	},
	"131" : 
	{
		"nbEvaluatedPrograms" : 24,
		"nbEvaluatedTeams" : 5,
		"nbExecutionForEachInstr" : 
		{
			"0" : 9,
			"1" : 7,
			"2" : 4,
			"3" : 1,
			"4" : 3,
			"5" : 1
		},
		"traceTeamIds" : "0, 2, 8, 15, 20"
	},
	"132" : 
	{
		"nbEvaluatedPrograms" : 29,
		"nbEvaluatedTeams" : 7,
		"nbExecutionForEachInstr" : 
		{
			"0" : 9,
			"1" : 7,
			"2" : 4,
			"3" : 3,
			"4" : 5,
			"5" : 2
		},
		"traceTeamIds" : "0, 2, 8, 15, 7, 19, 26"
	},
	"133" : 
	{
		"nbEvaluatedPrograms" : 24,
		"nbEvaluatedTeams" : 5,
		"nbExecutionForEachInstr" : 
		{
			"0" : 9,
			"1" : 7,
			"2" : 4,
			"3" : 1,
			"4" : 3,
			"5" : 1
		},
		"traceTeamIds" : "0, 2, 8, 15, 20"
	},
	"134" : 
	{
		"nbEvaluatedPrograms" : 24,
		"nbEvaluatedTeams" : 5,
		"nbExecutionForEachInstr" : 
		{
			"0" : 9,
			"1" : 7,
			"2" : 4,
			"3" : 1,
			"4" : 3,
			"5" : 1
		},
		"traceTeamIds" : "0, 2, 8, 15, 20"
	},
	"135" : 
	{
		"nbEvaluatedPrograms" : 20,
		"nbEvaluatedTeams" : 7,
		"nbExecutionForEachInstr" : 
		{
			"0" : 5,
			"1" : 4,
			"2" : 4,
			"3" : 3,
			"4" : 2,
			"5" : 1,
			"6" : 1
		},
		"traceTeamIds" : "0, 4, 11, 22, 30, 17, 24"
	},
	"136" : 
	{
		"nbEvaluatedPrograms" : 17,
		"nbEvaluatedTeams" : 6,
		"nbExecutionForEachInstr" : 
		{
			"0" : 3,
			"1" : 4,
			"2" : 3,
			"3" : 4,
			"4" : 3,
			"5" : 2,
			"6" : 1
		},
		"traceTeamIds" : "0, 4, 11, 23, 7, 17"
	},
	"137" : 
	{
		"nbEvaluatedPrograms" : 24,
		"nbEvaluatedTeams" : 5,
		"nbExecutionForEachInstr" : 
		{
			"0" : 9,
			"1" : 7,
			"2" : 4,
			"3" : 1,
			"4" : 3,
			"5" : 1
		},
		"traceTeamIds" : "0, 2, 8, 15, 20"
	},
	"138" : 
	{
		"nbEvaluatedPrograms" : 30,
		"nbEvaluatedTeams" : 7,
		"nbExecutionForEachInstr" : 
		{
			"0" : 12,
			"1" : 8,
			"2" : 3,
			"3" : 1,
			"4" : 5,
			"5" : 1
		},
		"traceTeamIds" : "0, 2, 8, 5, 12, 17, 24"
	},
	"139" : 
	{
		"nbEvaluatedPrograms" : 18,
		"nbEvaluatedTeams" : 5,
		"nbExecutionForEachInstr" : 
		{
			"0" : 6,
			"1" : 4,
			"2" : 3,
			"3" : 2,
			"4" : 4,
			"5" : 1
		},
		"traceTeamIds" : "0, 3, 5, 13, 7"
	},
	"14" : 
	{
		"nbEvaluatedPrograms" : 15,
		"nbEvaluatedTeams" : 5,
		"nbExecutionForEachInstr" : 
		{
			"0" : 4,
			"1" : 3,
			"2" : 4,
			"3" : 3,
			"4" : 1,
			"5" : 1
		},
		"traceTeamIds" : "0, 4, 11, 22, 20"
	},
	"140" : 
	{
		"nbEvaluatedPrograms" : 27,
		"nbEvaluatedTeams" : 6,
		"nbExecutionForEachInstr" : 
		{
			"0" : 9,
			"1" : 8,
			"2" : 4,
			"3" : 1,
			"4" : 3,
			"5" : 3
		},
		"traceTeamIds" : "0, 2, 8, 15, 20, 28"
	},
	"141" : 
	{
		"nbEvaluatedPrograms" : 20,
		"nbEvaluatedTeams" : 5,
		"nbExecutionForEachInstr" : 
		{
			"0" : 7,
			"1" : 4,
			"2" : 6,
			"3" : 1,
			"4" : 1,
			"5" : 1
		},
		"traceTeamIds" : "0, 3, 10, 15, 20"
	},
	"142" : 
	{
		"nbEvaluatedPrograms" : 13,
		"nbEvaluatedTeams" : 5,
		"nbExecutionForEachInstr" : 
		{
			"0" : 2,
			"1" : 3,
			"2" : 3,
			"3" : 3,
			"4" : 3,
			"5" : 1
		},
		"traceTeamIds" : "0, 4, 11, 23, 7"
	},
	"143" : 
	{
		"nbEvaluatedPrograms" : 21,
		"nbEvaluatedTeams" : 6,
		"nbExecutionForEachInstr" : 
		{
			"0" : 8,
			"1" : 4,
			"2" : 3,
			"3" : 2,
			"4" : 4,
			"5" : 2
		},
		"traceTeamIds" : "0, 1, 6, 16, 27, 26"
	},
	"144" : 
	{
		"nbEvaluatedPrograms" : 18,
		"nbEvaluatedTeams" : 5,
		"nbExecutionForEachInstr" : 
		{
			"0" : 7,
			"1" : 4,
			"2" : 3,
			"4" : 3
		},
		"traceTeamIds" : "0, 3, 5, 12, 24"
	},
	"145" : 
	{
		"nbEvaluatedPrograms" : 23,
		"nbEvaluatedTeams" : 5,
		"nbExecutionForEachInstr" : 
		{
			"0" : 9,
			"1" : 5,
			"2" : 3,
			"3" : 3,
			"4" : 4,
			"5" : 2
		},
		"traceTeamIds" : "0, 1, 6, 7, 17"
	},
	"146" : 
	{
		"nbEvaluatedPrograms" : 29,
		"nbEvaluatedTeams" : 7,
		"nbExecutionForEachInstr" : 
		{
			"0" : 9,
			"1" : 7,
			"2" : 4,
			"3" : 3,
			"4" : 5,
			"5" : 2
		},
		"traceTeamIds" : "0, 2, 8, 15, 7, 19, 26"
	},
	"147" : 
	{
		"nbEvaluatedPrograms" : 25,
		"nbEvaluatedTeams" : 7,
		"nbExecutionForEachInstr" : 
		{
			"0" : 7,
			"1" : 4,
			"2" : 6,
			"3" : 3,
			"4" : 3,
			"5" : 2
		},
		"traceTeamIds" : "0, 3, 10, 15, 7, 19, 26"
	},
	"148" : 
	{
		"nbEvaluatedPrograms" : 18,
		"nbEvaluatedTeams" : 6,
		"nbExecutionForEachInstr" : 
		{
			"0" : 5,
			"1" : 3,
			"2" : 4,
			"3" : 3,
			"4" : 2,
			"5" : 1,
			"6" : 1
		},
		"traceTeamIds" : "0, 4, 11, 22, 30, 17"
	},
	"149" : 
	{
		"nbEvaluatedPrograms" : 25,
		"nbEvaluatedTeams" : 7,
		"nbExecutionForEachInstr" : 
		{
			"0" : 10,
			"1" : 4,
			"2" : 3,
			"3" : 1,
			"4" : 7,
			"5" : 1
		},
		"traceTeamIds" : "0, 1, 6, 5, 12, 19, 26"
	},
	"15" : 
	{
		"nbEvaluatedPrograms" : 29,
		"nbEvaluatedTeams" : 6,
		"nbExecutionForEachInstr" : 
		{
			"0" : 10,
			"1" : 8,
			"2" : 4,
			"3" : 3,
			"4" : 4,
			"5" : 2
		},
		"traceTeamIds" : "0, 2, 8, 15, 7, 17"
	},
	"150" : 
	{
		"nbEvaluatedPrograms" : 27,
		"nbEvaluatedTeams" : 6,
		"nbExecutionForEachInstr" : 
		{
			"0" : 9,
			"1" : 8,
			"2" : 4,
			"3" : 1,
			"4" : 3,
			"5" : 3
		},
		"traceTeamIds" : "0, 2, 8, 15, 20, 28"
	},
	"151" : 
	{
		"nbEvaluatedPrograms" : 30,
		"nbEvaluatedTeams" : 7,
		"nbExecutionForEachInstr" : 
		{
			"0" : 12,
			"1" : 8,
			"2" : 3,
			"3" : 1,
			"4" : 5,
			"5" : 1
		},
		"traceTeamIds" : "0, 2, 8, 5, 12, 17, 24"
	},
	"152" : 
	{
		"nbEvaluatedPrograms" : 18,
		"nbEvaluatedTeams" : 6,
		"nbExecutionForEachInstr" : 
		{
			"0" : 5,
			"1" : 3,
			"2" : 4,
			"3" : 3,
			"4" : 2,
			"5" : 1,
			"6" : 1
		},
		"traceTeamIds" : "0, 4, 11, 22, 30, 17"
	},
	"153" : 
	{
		"nbEvaluatedPrograms" : 18,
		"nbEvaluatedTeams" : 5,
		"nbExecutionForEachInstr" : 
		{
			"0" : 6,
			"1" : 4,
			"2" : 3,
			"3" : 2,
			"4" : 4,
			"5" : 1
		},
		"traceTeamIds" : "0, 3, 5, 13, 7"
	},
	"154" : 
	{
		"nbEvaluatedPrograms" : 29,
		"nbEvaluatedTeams" : 6,
		"nbExecutionForEachInstr" : 
		{
			"0" : 10,
			"1" : 8,
			"2" : 4,
			"3" : 3,
			"4" : 4,
			"5" : 2
		},
		"traceTeamIds" : "0, 2, 8, 15, 7, 17"
	},
	"155" : 
	{
		"nbEvaluatedPrograms" : 20,
		"nbEvaluatedTeams" : 7,
		"nbExecutionForEachInstr" : 
		{
			"0" : 5,
			"1" : 4,
			"2" : 4,
			"3" : 3,
			"4" : 2,
			"5" : 1,
			"6" : 1
		},
		"traceTeamIds" : "0, 4, 11, 22, 30, 17, 24"
	},
	"156" : 
	{
		"nbEvaluatedPrograms" : 13,
		"nbEvaluatedTeams" : 5,
		"nbExecutionForEachInstr" : 
		{
			"0" : 2,
			"1" : 3,
			"2" : 3,
			"3" : 3,
			"4" : 3,
			"5" : 1
		},
		"traceTeamIds" : "0, 4, 11, 23, 7"
	},
	"157" : 
	{
		"nbEvaluatedPrograms" : 14,
		"nbEvaluatedTeams" : 3,
		"nbExecutionForEachInstr" : 
		{
			"0" : 5,
			"1" : 3,
			"2" : 3,
			"3" : 2,
			"4" : 1,
			"5" : 1
		},
		"traceTeamIds" : "0, 3, 7"
	},
	"159" : 
	{
		"nbEvaluatedPrograms" : 23,
		"nbEvaluatedTeams" : 6,
		"nbExecutionForEachInstr" : 
		{
			"0" : 8,
			"1" : 4,
			"2" : 3,
			"3" : 3,
			"4" : 5,
			"5" : 2
		},
		"traceTeamIds" : "0, 1, 6, 7, 19, 26"
	},
	"16" : 
	{
		"nbEvaluatedPrograms" : 20,
		"nbEvaluatedTeams" : 6,
		"nbExecutionForEachInstr" : 
		{
			"0" : 7,
			"1" : 3,
			"2" : 3,
			"3" : 1,
			"4" : 4,
			"5" : 1
		},
		"traceTeamIds" : "0, 3, 5, 12, 19, 26"
	},
	"160" : 
	{
		"nbEvaluatedPrograms" : 22,
		"nbEvaluatedTeams" : 4,
		"nbExecutionForEachInstr" : 
		{
			"0" : 9,
			"1" : 6,
			"2" : 3,
			"3" : 2,
			"4" : 3,
			"5" : 1
		},
		"traceTeamIds" : "0, 2, 8, 7"
	},
	"161" : 
	{
		"nbEvaluatedPrograms" : 26,
		"nbEvaluatedTeams" : 6,
		"nbExecutionForEachInstr" : 
		{
			"0" : 10,
			"1" : 7,
			"2" : 3,
			"3" : 2,
			"4" : 6,
			"5" : 1
		},
		"traceTeamIds" : "0, 2, 8, 5, 13, 7"
	},
	"162" : 
	{
		"nbEvaluatedPrograms" : 26,
		"nbEvaluatedTeams" : 5,
		"nbExecutionForEachInstr" : 
		{
			"0" : 10,
			"1" : 7,
			"2" : 3,
			"3" : 3,
			"4" : 3,
			"5" : 2
		},
		"traceTeamIds" : "0, 2, 8, 7, 17"
	},
	"163" : 
	{
		"nbEvaluatedPrograms" : 23,
		"nbEvaluatedTeams" : 6,
		"nbExecutionForEachInstr" : 
		{
			"0" : 7,
			"1" : 5,
			"2" : 6,
			"3" : 1,
			"4" : 1,
			"5" : 3
		},
		"traceTeamIds" : "0, 3, 10, 15, 20, 28"
	},
	"164" : 
	{
		"nbEvaluatedPrograms" : 16,
		"nbEvaluatedTeams" : 6,
		"nbExecutionForEachInstr" : 
		{
			"0" : 4,
			"1" : 3,
			"2" : 4,
			"3" : 2,
			"4" : 2,
			"5" : 2,
			"6" : 1
		},
		"traceTeamIds" : "0, 4, 11, 22, 30, 24"
	},
	"165" : 
	{
		"nbEvaluatedPrograms" : 21,
		"nbEvaluatedTeams" : 6,
		"nbExecutionForEachInstr" : 
		{
			"0" : 8,
			"1" : 4,
			"2" : 3,
			"3" : 2,
			"4" : 4,
			"5" : 2
		},
		"traceTeamIds" : "0, 1, 6, 16, 27, 26"
	},
	"166" : 
	{
		"nbEvaluatedPrograms" : 18,
		"nbEvaluatedTeams" : 5,
		"nbExecutionForEachInstr" : 
		{
			"0" : 7,
			"1" : 4,
			"2" : 3,
			"4" : 3
		},
		"traceTeamIds" : "0, 3, 5, 12, 24"
	},
	"167" : 
	{
		"nbEvaluatedPrograms" : 31,
		"nbEvaluatedTeams" : 7,
		"nbExecutionForEachInstr" : 
		{
			"0" : 10,
			"1" : 9,
			"2" : 4,
			"3" : 3,
			"4" : 4,
			"5" : 2
		},
		"traceTeamIds" : "0, 2, 8, 15, 7, 17, 24"
	},
	"169" : 
	{
		"nbEvaluatedPrograms" : 18,
		"nbEvaluatedTeams" : 6,
		"nbExecutionForEachInstr" : 
		{
			"0" : 5,
			"1" : 3,
			"2" : 4,
			"3" : 3,
			"4" : 2,
			"5" : 1,
			"6" : 1
		},
		"traceTeamIds" : "0, 4, 11, 22, 30, 17"
	},
	"17" : 
	{
		"nbEvaluatedPrograms" : 18,
		"nbEvaluatedTeams" : 6,
		"nbExecutionForEachInstr" : 
		{
			"0" : 5,
			"1" : 3,
			"2" : 4,
			"3" : 3,
			"4" : 2,
			"5" : 1,
			"6" : 1
		},
		"traceTeamIds" : "0, 4, 11, 22, 30, 17"
	},
	"170" : 
	{
		"nbEvaluatedPrograms" : 24,
		"nbEvaluatedTeams" : 5,
		"nbExecutionForEachInstr" : 
		{
			"0" : 9,
			"1" : 7,
			"2" : 4,
			"3" : 1,
			"4" : 3,
			"5" : 1
		},
		"traceTeamIds" : "0, 2, 8, 15, 20"
	},
	"171" : 
	{
		"nbEvaluatedPrograms" : 32,
		"nbEvaluatedTeams" : 8,
		"nbExecutionForEachInstr" : 
		{
			"0" : 11,
			"1" : 9,
			"2" : 3,
			"3" : 3,
			"4" : 6,
			"5" : 2
		},
		"traceTeamIds" : "0, 2, 8, 5, 13, 7, 17, 24"
	},
	"172" : 
	{
		"nbEvaluatedPrograms" : 18,
		"nbEvaluatedTeams" : 6,
		"nbExecutionForEachInstr" : 
		{
			"0" : 5,
			"1" : 3,
			"2" : 4,
			"3" : 3,
			"4" : 2,
			"5" : 1,
			"6" : 1
		},
		"traceTeamIds" : "0, 4, 11, 22, 30, 17"
	},
	"174" : 
	{
		"nbEvaluatedPrograms" : 17,
		"nbEvaluatedTeams" : 6,
		"nbExecutionForEachInstr" : 
		{
			"0" : 4,
			"1" : 4,
			"2" : 4,
			"3" : 3,
			"4" : 1,
			"5" : 1
		},
		"traceTeamIds" : "0, 4, 11, 22, 20, 24"
	},
	"175" : 
	{
		"nbEvaluatedPrograms" : 27,
		"nbEvaluatedTeams" : 6,
		"nbExecutionForEachInstr" : 
		{
			"0" : 9,
			"1" : 8,
			"2" : 4,
			"3" : 1,
			"4" : 3,
			"5" : 3
		},
		"traceTeamIds" : "0, 2, 8, 15, 20, 28"
	},
	"176" : 
	{
		"nbEvaluatedPrograms" : 26,
		"nbEvaluatedTeams" : 6,
		"nbExecutionForEachInstr" : 
		{
			"0" : 11,
			"1" : 7,
			"2" : 3,
			"3" : 2,
			"4" : 5,
			"5" : 1
		},
		"traceTeamIds" : "0, 2, 8, 5, 12, 24"
	},
	"177" : 
	{
		"nbEvaluatedPrograms" : 15,
		"nbEvaluatedTeams" : 5,
		"nbExecutionForEachInstr" : 
		{
			"0" : 4,
			"1" : 3,
			"2" : 4,
			"3" : 3,
			"4" : 1,
			"5" : 1
		},
		"traceTeamIds" : "0, 4, 11, 22, 20"
	},
	"178" : 
	{
		"nbEvaluatedPrograms" : 26,
		"nbEvaluatedTeams" : 6,
		"nbExecutionForEachInstr" : 
		{
			"0" : 10,
			"1" : 7,
			"2" : 3,
			"3" : 2,
			"4" : 6,
			"5" : 1
		},
		"traceTeamIds" : "0, 2, 8, 5, 13, 7"
	},
	"179" : 
	{
		"nbEvaluatedPrograms" : 25,
		"nbEvaluatedTeams" : 6,
		"nbExecutionForEachInstr" : 
		{
			"0" : 11,
			"1" : 5,
			"2" : 3,
			"3" : 1,
			"4" : 6,
			"5" : 1
		},
		"traceTeamIds" : "0, 1, 6, 5, 12, 17"
	},
	"18" : 
	{
		"nbEvaluatedPrograms" : 25,
		"nbEvaluatedTeams" : 6,
		"nbExecutionForEachInstr" : 
		{
			"0" : 11,
			"1" : 5,
			"2" : 3,
			"3" : 1,
			"4" : 6,
			"5" : 1
		},
		"traceTeamIds" : "0, 1, 6, 5, 12, 17"
	},
	"180" : 
	{
		"nbEvaluatedPrograms" : 15,
		"nbEvaluatedTeams" : 5,
		"nbExecutionForEachInstr" : 
		{
			"0" : 4,
			"1" : 3,
			"2" : 4,
			"3" : 3,
			"4" : 1,
			"5" : 1
		},
		"traceTeamIds" : "0, 4, 11, 22, 20"
	},
	"181" : 
	{
		"nbEvaluatedPrograms" : 21,
		"nbEvaluatedTeams" : 6,
		"nbExecutionForEachInstr" : 
		{
			"0" : 8,
			"1" : 4,
			"2" : 3,
			"3" : 2,
			"4" : 4,
			"5" : 2
		},
		"traceTeamIds" : "0, 1, 6, 16, 27, 26"
	},
	"182" : 
	{
		"nbEvaluatedPrograms" : 29,
		"nbEvaluatedTeams" : 7,
		"nbExecutionForEachInstr" : 
		{
			"0" : 9,
			"1" : 7,
			"2" : 4,
			"3" : 3,
			"4" : 5,
			"5" : 2
		},
		"traceTeamIds" : "0, 2, 8, 15, 7, 19, 26"
	},
	"183" : 
	{
		"nbEvaluatedPrograms" : 20,
		"nbEvaluatedTeams" : 7,
		"nbExecutionForEachInstr" : 
		{
			"0" : 5,
			"1" : 4,
			"2" : 4,
			"3" : 3,
			"4" : 2,
			"5" : 1,
			"6" : 1
		},
		"traceTeamIds" : "0, 4, 11, 22, 30, 17, 24"
	},
	"184" : 
	{
		"nbEvaluatedPrograms" : 20,
		"nbEvaluatedTeams" : 6,
		"nbExecutionForEachInstr" : 
		{
			"0" : 7,
			"1" : 3,
			"2" : 3,
			"3" : 1,
			"4" : 4,
			"5" : 1
		},
		"traceTeamIds" : "0, 3, 5, 12, 19, 26"
	},
	"185" : 
	{
		"nbEvaluatedPrograms" : 18,
		"nbEvaluatedTeams" : 5,
		"nbExecutionForEachInstr" : 
		{
			"0" : 6,
			"1" : 4,
			"2" : 3,
			"3" : 2,
			"4" : 4,
			"5" : 1
		},
		"traceTeamIds" : "0, 3, 5, 13, 7"
	},
	"186" : 
	{
		"nbEvaluatedPrograms" : 25,
		"nbEvaluatedTeams" : 6,
		"nbExecutionForEachInstr" : 
		{
			"0" : 11,
			"1" : 5,
			"2" : 3,
			"3" : 1,
			"4" : 6,
			"5" : 1
		},
		"traceTeamIds" : "0, 1, 6, 5, 12, 17"
	},
	"187" : 
	{
		"nbEvaluatedPrograms" : 23,
		"nbEvaluatedTeams" : 5,
		"nbExecutionForEachInstr" : 
		{
			"0" : 9,
			"1" : 5,
			"2" : 3,
			"3" : 3,
			"4" : 4,
			"5" : 2
		},
		"traceTeamIds" : "0, 1, 6, 7, 17"
	},
	"188" : 
	{
		"nbEvaluatedPrograms" : 20,
		"nbEvaluatedTeams" : 7,
		"nbExecutionForEachInstr" : 
		{
			"0" : 5,
			"1" : 4,
			"2" : 4,
			"3" : 3,
			"4" : 2,
			"5" : 1,
			"6" : 1
		},
		"traceTeamIds" : "0, 4, 11, 22, 30, 17, 24"
	},
	"189" : 
	{
		"nbEvaluatedPrograms" : 23,
		"nbEvaluatedTeams" : 6,
		"nbExecutionForEachInstr" : 
		{
			"0" : 8,
			"1" : 4,
			"2" : 3,
			"3" : 3,
			"4" : 5,
			"5" : 2
		},
		"traceTeamIds" : "0, 1, 6, 7, 19, 26"
	},
	"19" : 
	{
		"nbEvaluatedPrograms" : 17,
		"nbEvaluatedTeams" : 6,
		"nbExecutionForEachInstr" : 
		{
			"0" : 4,
			"1" : 4,
			"2" : 4,
			"3" : 3,
			"4" : 1,
			"5" : 1
		},
		"traceTeamIds" : "0, 4, 11, 22, 20, 24"
	},
	"190" : 
	{
		"nbEvaluatedPrograms" : 29,
		"nbEvaluatedTeams" : 7,
		"nbExecutionForEachInstr" : 
		{
			"0" : 9,
			"1" : 7,
			"2" : 4,
			"3" : 3,
			"4" : 5,
			"5" : 2
		},
		"traceTeamIds" : "0, 2, 8, 15, 7, 19, 26"
	},
	"191" : 
	{
		"nbEvaluatedPrograms" : 26,
		"nbEvaluatedTeams" : 6,
		"nbExecutionForEachInstr" : 
		{
			"0" : 10,
			"1" : 7,
			"2" : 3,
			"3" : 2,
			"4" : 6,
			"5" : 1
		},
		"traceTeamIds" : "0, 2, 8, 5, 13, 7"
	},
	"192" : 
	{
		"nbEvaluatedPrograms" : 20,
		"nbEvaluatedTeams" : 5,
		"nbExecutionForEachInstr" : 
		{
			"0" : 7,
			"1" : 4,
			"2" : 6,
			"3" : 1,
			"4" : 1,
			"5" : 1
		},
		"traceTeamIds" : "0, 3, 10, 15, 20"
	},
	"195" : 
	{
		"nbEvaluatedPrograms" : 31,
		"nbEvaluatedTeams" : 7,
		"nbExecutionForEachInstr" : 
		{
			"0" : 10,
			"1" : 9,
			"2" : 4,
			"3" : 3,
			"4" : 4,
			"5" : 2
		},
		"traceTeamIds" : "0, 2, 8, 15, 7, 17, 24"
	},
	"197" : 
	{
		"nbEvaluatedPrograms" : 19,
		"nbEvaluatedTeams" : 7,
		"nbExecutionForEachInstr" : 
		{
			"0" : 3,
			"1" : 5,
			"2" : 3,
			"3" : 4,
			"4" : 3,
			"5" : 2
		},
		"traceTeamIds" : "0, 4, 11, 23, 7, 17, 24"
	},
	"198" : 
	{
		"nbEvaluatedPrograms" : 23,
		"nbEvaluatedTeams" : 6,
		"nbExecutionForEachInstr" : 
		{
			"0" : 7,
			"1" : 5,
			"2" : 6,
			"3" : 1,
			"4" : 1,
			"5" : 3
		},
		"traceTeamIds" : "0, 3, 10, 15, 20, 28"
	},
	"199" : 
	{
		"nbEvaluatedPrograms" : 28,
		"nbEvaluatedTeams" : 7,
		"nbExecutionForEachInstr" : 
		{
			"0" : 11,
			"1" : 6,
			"2" : 3,
			"3" : 1,
			"4" : 6,
			"5" : 1
		},
		"traceTeamIds" : "0, 2, 8, 5, 12, 19, 26"
	},
	"2" : 
	{
		"nbEvaluatedPrograms" : 19,
		"nbEvaluatedTeams" : 5,
		"nbExecutionForEachInstr" : 
		{
			"0" : 8,
			"1" : 4,
			"2" : 3,
			"3" : 2,
			"4" : 4,
			"5" : 1
		},
		"traceTeamIds" : "0, 1, 6, 16, 27"
	},
	"20" : 
	{
		"nbEvaluatedPrograms" : 29,
		"nbEvaluatedTeams" : 7,
		"nbExecutionForEachInstr" : 
		{
			"0" : 9,
			"1" : 7,
			"2" : 4,
			"3" : 3,
			"4" : 5,
			"5" : 2
		},
		"traceTeamIds" : "0, 2, 8, 15, 7, 19, 26"
	},
	"21" : 
	{
		"nbEvaluatedPrograms" : 17,
		"nbEvaluatedTeams" : 6,
		"nbExecutionForEachInstr" : 
		{
			"0" : 3,
			"1" : 4,
			"2" : 3,
			"3" : 4,
			"4" : 3,
			"5" : 2
		},
		"traceTeamIds" : "0, 4, 11, 23, 7, 17"
	},
	"22" : 
	{
		"nbEvaluatedPrograms" : 28,
		"nbEvaluatedTeams" : 7,
		"nbExecutionForEachInstr" : 
		{
			"0" : 11,
			"1" : 6,
			"2" : 3,
			"3" : 1,
			"4" : 6,
			"5" : 1
		},
		"traceTeamIds" : "0, 2, 8, 5, 12, 19, 26"
	},
	"23" : 
	{
		"nbEvaluatedPrograms" : 17,
		"nbEvaluatedTeams" : 6,
		"nbExecutionForEachInstr" : 
		{
			"0" : 3,
			"1" : 4,
			"2" : 3,
			"3" : 4,
			"4" : 3,
			"5" : 2
		},
		"traceTeamIds" : "0, 4, 11, 23, 7, 17"
	},
	"24" : 
	{
		"nbEvaluatedPrograms" : 15,
		"nbEvaluatedTeams" : 5,
		"nbExecutionForEachInstr" : 
		{
			"0" : 4,
			"1" : 3,
			"2" : 4,
			"3" : 3,
			"4" : 1,
			"5" : 1
		},
		"traceTeamIds" : "0, 4, 11, 22, 20"
	},
	"25" : 
	{
		"nbEvaluatedPrograms" : 17,
		"nbEvaluatedTeams" : 6,
		"nbExecutionForEachInstr" : 
		{
			"0" : 3,
			"1" : 4,
			"2" : 3,
			"3" : 4,
			"4" : 3,
			"5" : 2
		},
		"traceTeamIds" : "0, 4, 11, 23, 7, 17"
	},
	"26" : 
	{
		"nbEvaluatedPrograms" : 20,
		"nbEvaluatedTeams" : 6,
		"nbExecutionForEachInstr" : 
		{
			"0" : 7,
			"1" : 3,
			"2" : 3,
			"3" : 1,
			"4" : 4,
			"5" : 1
		},
		"traceTeamIds" : "0, 3, 5, 12, 19, 26"
	},
	"27" : 
	{
		"nbEvaluatedPrograms" : 20,
		"nbEvaluatedTeams" : 7,
		"nbExecutionForEachInstr" : 
		{
			"0" : 5,
			"1" : 4,
			"2" : 4,
			"3" : 3,
			"4" : 2,
			"5" : 1,
			"6" : 1
		},
		"traceTeamIds" : "0, 4, 11, 22, 30, 17, 24"
	},
	"28" : 
	{
		"nbEvaluatedPrograms" : 20,
		"nbEvaluatedTeams" : 6,
		"nbExecutionForEachInstr" : 
		{
			"0" : 7,
			"1" : 3,
			"2" : 3,
			"3" : 1,
			"4" : 4,
			"5" : 1
		},
		"traceTeamIds" : "0, 3, 5, 12, 19, 26"
	},
	"29" : 
	{
		"nbEvaluatedPrograms" : 18,
		"nbEvaluatedTeams" : 5,
		"nbExecutionForEachInstr" : 
		{
			"0" : 6,
			"1" : 4,
			"2" : 3,
			"3" : 2,
			"4" : 4,
			"5" : 1
		},
		"traceTeamIds" : "0, 3, 5, 13, 7"
	},
	"3" : 
	{
		"nbEvaluatedPrograms" : 24,
		"nbEvaluatedTeams" : 5,
		"nbExecutionForEachInstr" : 
		{
			"0" : 9,
			"1" : 7,
			"2" : 4,
			"3" : 1,
			"4" : 3,
			"5" : 1
		},
		"traceTeamIds" : "0, 2, 8, 15, 20"
	},
	"30" : 
	{
		"nbEvaluatedPrograms" : 19,
		"nbEvaluatedTeams" : 5,
		"nbExecutionForEachInstr" : 
		{
			"0" : 8,
			"1" : 4,
			"2" : 3,
			"3" : 2,
			"4" : 4,
			"5" : 1
		},
		"traceTeamIds" : "0, 1, 6, 16, 27"
	},
	"31" : 
	{
		"nbEvaluatedPrograms" : 13,
		"nbEvaluatedTeams" : 5,
		"nbExecutionForEachInstr" : 
		{
			"0" : 2,
			"1" : 3,
			"2" : 3,
			"3" : 3,
			"4" : 3,
			"5" : 1,
			"6" : 1
		},
		"traceTeamIds" : "0, 4, 11, 23, 7"
	},
	"32" : 
	{
		"nbEvaluatedPrograms" : 28,
		"nbEvaluatedTeams" : 7,
		"nbExecutionForEachInstr" : 
		{
			"0" : 11,
			"1" : 6,
			"2" : 3,
			"3" : 1,
			"4" : 6,
			"5" : 1
		},
		"traceTeamIds" : "0, 2, 8, 5, 12, 19, 26"
	},
	"33" : 
	{
		"nbEvaluatedPrograms" : 20,
		"nbEvaluatedTeams" : 7,
		"nbExecutionForEachInstr" : 
		{
			"0" : 5,
			"1" : 4,
			"2" : 4,
			"3" : 3,
			"4" : 2,
			"5" : 1,
			"6" : 1
		},
		"traceTeamIds" : "0, 4, 11, 22, 30, 17, 24"
	},
	"34" : 
	{
		"nbEvaluatedPrograms" : 28,
		"nbEvaluatedTeams" : 7,
		"nbExecutionForEachInstr" : 
		{
			"0" : 11,
			"1" : 6,
			"2" : 3,
			"3" : 1,
			"4" : 6,
			"5" : 1
		},
		"traceTeamIds" : "0, 2, 8, 5, 12, 19, 26"
	},
	"35" : 
	{
		"nbEvaluatedPrograms" : 21,
		"nbEvaluatedTeams" : 6,
		"nbExecutionForEachInstr" : 
		{
			"0" : 8,
			"1" : 4,
			"2" : 3,
			"3" : 2,
			"4" : 4,
			"5" : 2
		},
		"traceTeamIds" : "0, 1, 6, 16, 27, 26"
	},
	"36" : 
	{
		"nbEvaluatedPrograms" : 18,
		"nbEvaluatedTeams" : 6,
		"nbExecutionForEachInstr" : 
		{
			"0" : 5,
			"1" : 3,
			"2" : 4,
			"3" : 3,
			"4" : 2,
			"5" : 1,
			"6" : 1
		},
		"traceTeamIds" : "0, 4, 11, 22, 30, 17"
	},
	"37" : 
	{
		"nbEvaluatedPrograms" : 23,
		"nbEvaluatedTeams" : 6,
		"nbExecutionForEachInstr" : 
		{
			"0" : 7,
			"1" : 5,
			"2" : 6,
			"3" : 1,
			"4" : 1,
			"5" : 3
		},
		"traceTeamIds" : "0, 3, 10, 15, 20, 28"
	},
	"38" : 
	{
		"nbEvaluatedPrograms" : 29,
		"nbEvaluatedTeams" : 7,
		"nbExecutionForEachInstr" : 
		{
			"0" : 9,
			"1" : 7,
			"2" : 4,
			"3" : 3,
			"4" : 5,
			"5" : 2
		},
		"traceTeamIds" : "0, 2, 8, 15, 7, 19, 26"
	},
	"39" : 
	{
		"nbEvaluatedPrograms" : 25,
		"nbEvaluatedTeams" : 7,
		"nbExecutionForEachInstr" : 
		{
			"0" : 10,
			"1" : 4,
			"2" : 3,
			"3" : 1,
			"4" : 7,
			"5" : 1
		},
		"traceTeamIds" : "0, 1, 6, 5, 12, 19, 26"
	},
	"4" : 
	{
		"nbEvaluatedPrograms" : 26,
		"nbEvaluatedTeams" : 5,
		"nbExecutionForEachInstr" : 
		{
			"0" : 10,
			"1" : 7,
			"2" : 3,
			"3" : 3,
			"4" : 3,
			"5" : 2
		},
		"traceTeamIds" : "0, 2, 8, 7, 17"
	},
	"40" : 
	{
		"nbEvaluatedPrograms" : 19,
		"nbEvaluatedTeams" : 4,
		"nbExecutionForEachInstr" : 
		{
			"0" : 8,
			"1" : 4,
			"2" : 3,
			"3" : 2,
			"4" : 4,
			"5" : 1
		},
		"traceTeamIds" : "0, 1, 6, 7"
	},
	"41" : 
	{
		"nbEvaluatedPrograms" : 25,
		"nbEvaluatedTeams" : 5,
		"nbExecutionForEachInstr" : 
		{
			"0" : 9,
			"1" : 7,
			"2" : 4,
			"3" : 2,
			"4" : 4,
			"5" : 1
		},
		"traceTeamIds" : "0, 2, 8, 15, 7"
	},
	"42" : 
	{
		"nbEvaluatedPrograms" : 18,
		"nbEvaluatedTeams" : 6,
		"nbExecutionForEachInstr" : 
		{
			"0" : 5,
			"1" : 3,
			"2" : 4,
			"3" : 3,
			"4" : 2,
			"5" : 1,
			"6" : 1
		},
		"traceTeamIds" : "0, 4, 11, 22, 30, 17"
	},
	"43" : 
	{
		"nbEvaluatedPrograms" : 20,
		"nbEvaluatedTeams" : 6,
		"nbExecutionForEachInstr" : 
		{
			"0" : 7,
			"1" : 3,
			"2" : 3,
			"3" : 1,
			"4" : 4,
			"5" : 1
		},
		"traceTeamIds" : "0, 3, 5, 12, 19, 26"
	},
	"44" : 
	{
		"nbEvaluatedPrograms" : 17,
		"nbEvaluatedTeams" : 6,
		"nbExecutionForEachInstr" : 
		{
			"0" : 3,
			"1" : 4,
			"2" : 3,
			"3" : 4,
			"4" : 3,
			"5" : 2
		},
		"traceTeamIds" : "0, 4, 11, 23, 7, 17"
	},
	"45" : 
	{
		"nbEvaluatedPrograms" : 19,
		"nbEvaluatedTeams" : 5,
		"nbExecutionForEachInstr" : 
		{
			"0" : 8,
			"1" : 4,
			"2" : 3,
			"3" : 2,
			"4" : 4,
			"5" : 1
		},
		"traceTeamIds" : "0, 1, 6, 16, 27"
	},
	"46" : 
	{
		"nbEvaluatedPrograms" : 13,
		"nbEvaluatedTeams" : 5,
		"nbExecutionForEachInstr" : 
		{
			"0" : 2,
			"1" : 3,
			"2" : 3,
			"3" : 3,
			"4" : 3,
			"5" : 1
		},
		"traceTeamIds" : "0, 4, 11, 23, 7"
	},
	"47" : 
	{
		"nbEvaluatedPrograms" : 28,
		"nbEvaluatedTeams" : 7,
		"nbExecutionForEachInstr" : 
		{
			"0" : 11,
			"1" : 6,
			"2" : 3,
			"3" : 1,
			"4" : 6,
			"5" : 1
		},
		"traceTeamIds" : "0, 2, 8, 5, 12, 19, 26"
	},
	"48" : 
	{
		"nbEvaluatedPrograms" : 15,
		"nbEvaluatedTeams" : 5,
		"nbExecutionForEachInstr" : 
		{
			"0" : 4,
			"1" : 3,
			"2" : 4,
			"3" : 3,
			"4" : 1,
			"5" : 1
		},
		"traceTeamIds" : "0, 4, 11, 22, 20"
	},
	"49" : 
	{
		"nbEvaluatedPrograms" : 24,
		"nbEvaluatedTeams" : 5,
		"nbExecutionForEachInstr" : 
		{
			"0" : 9,
			"1" : 7,
			"2" : 4,
			"3" : 1,
			"4" : 3,
			"5" : 1
		},
		"traceTeamIds" : "0, 2, 8, 15, 20"
	},
	"5" : 
	{
		"nbEvaluatedPrograms" : 32,
		"nbEvaluatedTeams" : 8,
		"nbExecutionForEachInstr" : 
		{
			"0" : 11,
			"1" : 9,
			"2" : 3,
			"3" : 3,
			"4" : 6,
			"5" : 2
		},
		"traceTeamIds" : "0, 2, 8, 5, 13, 7, 17, 24"
	},
	"50" : 
	{
		"nbEvaluatedPrograms" : 17,
		"nbEvaluatedTeams" : 6,
		"nbExecutionForEachInstr" : 
		{
			"0" : 3,
			"1" : 4,
			"2" : 3,
			"3" : 4,
			"4" : 3,
			"5" : 2
		},
		"traceTeamIds" : "0, 4, 11, 23, 7, 17"
	},
	"51" : 
	{
		"nbEvaluatedPrograms" : 26,
		"nbEvaluatedTeams" : 6,
		"nbExecutionForEachInstr" : 
		{
			"0" : 9,
			"1" : 8,
			"2" : 4,
			"3" : 1,
			"4" : 3,
			"5" : 1
		},
		"traceTeamIds" : "0, 2, 8, 15, 20, 24"
	},
	"52" : 
	{
		"nbEvaluatedPrograms" : 28,
		"nbEvaluatedTeams" : 6,
		"nbExecutionForEachInstr" : 
		{
			"0" : 10,
			"1" : 8,
			"2" : 3,
			"3" : 3,
			"4" : 3,
			"5" : 2
		},
		"traceTeamIds" : "0, 2, 8, 7, 17, 24"
	},
	"53" : 
	{
		"nbEvaluatedPrograms" : 22,
		"nbEvaluatedTeams" : 4,
		"nbExecutionForEachInstr" : 
		{
			"0" : 9,
			"1" : 6,
			"2" : 3,
			"3" : 2,
			"4" : 3,
			"5" : 1
		},
		"traceTeamIds" : "0, 2, 8, 7"
	},
	"54" : 
	{
		"nbEvaluatedPrograms" : 19,
		"nbEvaluatedTeams" : 5,
		"nbExecutionForEachInstr" : 
		{
			"0" : 8,
			"1" : 4,
			"2" : 3,
			"3" : 2,
			"4" : 4,
			"5" : 1
		},
		"traceTeamIds" : "0, 1, 6, 16, 27"
	},
	"55" : 
	{
		"nbEvaluatedPrograms" : 26,
		"nbEvaluatedTeams" : 6,
		"nbExecutionForEachInstr" : 
		{
			"0" : 9,
			"1" : 6,
			"2" : 3,
			"3" : 3,
			"4" : 4,
			"5" : 2
		},
		"traceTeamIds" : "0, 2, 8, 7, 19, 26"
	},
	"56" : 
	{
		"nbEvaluatedPrograms" : 28,
		"nbEvaluatedTeams" : 6,
		"nbExecutionForEachInstr" : 
		{
			"0" : 10,
			"1" : 8,
			"2" : 3,
			"3" : 3,
			"4" : 3,
			"5" : 2
		},
		"traceTeamIds" : "0, 2, 8, 7, 17, 24"
	},
	"57" : 
	{
		"nbEvaluatedPrograms" : 26,
		"nbEvaluatedTeams" : 5,
		"nbExecutionForEachInstr" : 
		{
			"0" : 10,
			"1" : 7,
			"2" : 3,
			"3" : 3,
			"4" : 3,
			"5" : 2
		},
		"traceTeamIds" : "0, 2, 8, 7, 17"
	},
	"58" : 
	{
		"nbEvaluatedPrograms" : 28,
		"nbEvaluatedTeams" : 7,
		"nbExecutionForEachInstr" : 
		{
			"0" : 11,
			"1" : 6,
			"2" : 3,
			"3" : 1,
			"4" : 6,
			"5" : 1
		},
		"traceTeamIds" : "0, 2, 8, 5, 12, 19, 26"
	},
	"59" : 
	{
		"nbEvaluatedPrograms" : 23,
		"nbEvaluatedTeams" : 6,
		"nbExecutionForEachInstr" : 
		{
			"0" : 9,
			"1" : 5,
			"2" : 3,
			"3" : 2,
			"4" : 7,
			"5" : 1
		},
		"traceTeamIds" : "0, 1, 6, 5, 13, 7"
	},
	"6" : 
	{
		"nbEvaluatedPrograms" : 20,
		"nbEvaluatedTeams" : 6,
		"nbExecutionForEachInstr" : 
		{
			"0" : 7,
			"1" : 3,
			"2" : 3,
			"3" : 1,
			"4" : 4,
			"5" : 1
		},
		"traceTeamIds" : "0, 3, 5, 12, 19, 26"
	},
	"60" : 
	{
		"nbEvaluatedPrograms" : 24,
		"nbEvaluatedTeams" : 5,
		"nbExecutionForEachInstr" : 
		{
			"0" : 9,
			"1" : 7,
			"2" : 4,
			"3" : 1,
			"4" : 3,
			"5" : 1
		},
		"traceTeamIds" : "0, 2, 8, 15, 20"
	},
	"61" : 
	{
		"nbEvaluatedPrograms" : 13,
		"nbEvaluatedTeams" : 5,
		"nbExecutionForEachInstr" : 
		{
			"0" : 2,
			"1" : 3,
			"2" : 3,
			"3" : 3,
			"4" : 3,
			"5" : 1
		},
		"traceTeamIds" : "0, 4, 11, 23, 7"
	},
	"62" : 
	{
		"nbEvaluatedPrograms" : 17,
		"nbEvaluatedTeams" : 6,
		"nbExecutionForEachInstr" : 
		{
			"0" : 3,
			"1" : 4,
			"2" : 3,
			"3" : 4,
			"4" : 3,
			"5" : 2
		},
		"traceTeamIds" : "0, 4, 11, 23, 7, 17"
	},
	"63" : 
	{
		"nbEvaluatedPrograms" : 29,
		"nbEvaluatedTeams" : 6,
		"nbExecutionForEachInstr" : 
		{
			"0" : 10,
			"1" : 8,
			"2" : 4,
			"3" : 3,
			"4" : 4,
			"5" : 2
		},
		"traceTeamIds" : "0, 2, 8, 15, 7, 17"
	},
	"64" : 
	{
		"nbEvaluatedPrograms" : 27,
		"nbEvaluatedTeams" : 6,
		"nbExecutionForEachInstr" : 
		{
			"0" : 9,
			"1" : 8,
			"2" : 4,
			"3" : 1,
			"4" : 3,
			"5" : 3
		},
		"traceTeamIds" : "0, 2, 8, 15, 20, 28"
	},
	"65" : 
	{
		"nbEvaluatedPrograms" : 23,
		"nbEvaluatedTeams" : 6,
		"nbExecutionForEachInstr" : 
		{
			"0" : 7,
			"1" : 5,
			"2" : 6,
			"3" : 1,
			"4" : 1,
			"5" : 3
		},
		"traceTeamIds" : "0, 3, 10, 15, 20, 28"
	},
	"66" : 
	{
		"nbEvaluatedPrograms" : 27,
		"nbEvaluatedTeams" : 6,
		"nbExecutionForEachInstr" : 
		{
			"0" : 9,
			"1" : 8,
			"2" : 4,
			"3" : 1,
			"4" : 3,
			"5" : 3
		},
		"traceTeamIds" : "0, 2, 8, 15, 20, 28"
	},
	"67" : 
	{
		"nbEvaluatedPrograms" : 25,
		"nbEvaluatedTeams" : 7,
		"nbExecutionForEachInstr" : 
		{
			"0" : 7,
			"1" : 4,
			"2" : 6,
			"3" : 3,
			"4" : 3,
			"5" : 2
		},
		"traceTeamIds" : "0, 3, 10, 15, 7, 19, 26"
	},
	"68" : 
	{
		"nbEvaluatedPrograms" : 18,
		"nbEvaluatedTeams" : 6,
		"nbExecutionForEachInstr" : 
		{
			"0" : 5,
			"1" : 3,
			"2" : 4,
			"3" : 3,
			"4" : 2,
			"5" : 1,
			"6" : 1
		},
		"traceTeamIds" : "0, 4, 11, 22, 30, 17"
	},
	"69" : 
	{
		"nbEvaluatedPrograms" : 25,
		"nbEvaluatedTeams" : 7,
		"nbExecutionForEachInstr" : 
		{
			"0" : 10,
			"1" : 4,
			"2" : 3,
			"3" : 1,
			"4" : 7,
			"5" : 1
		},
		"traceTeamIds" : "0, 1, 6, 5, 12, 19, 26"
	},
	"7" : 
	{
		"nbEvaluatedPrograms" : 18,
		"nbEvaluatedTeams" : 6,
		"nbExecutionForEachInstr" : 
		{
			"0" : 5,
			"1" : 3,
			"2" : 4,
			"3" : 3,
			"4" : 2,
			"5" : 1,
			"6" : 1
		},
		"traceTeamIds" : "0, 4, 11, 22, 30, 17"
	},
	"70" : 
	{
		"nbEvaluatedPrograms" : 26,
		"nbEvaluatedTeams" : 6,
		"nbExecutionForEachInstr" : 
		{
			"0" : 9,
			"1" : 8,
			"2" : 4,
			"3" : 1,
			"4" : 3,
			"5" : 1
		},
		"traceTeamIds" : "0, 2, 8, 15, 20, 24"
	},
	"71" : 
	{
		"nbEvaluatedPrograms" : 31,
		"nbEvaluatedTeams" : 7,
		"nbExecutionForEachInstr" : 
		{
			"0" : 10,
			"1" : 9,
			"2" : 4,
			"3" : 3,
			"4" : 4,
			"5" : 2
		},
		"traceTeamIds" : "0, 2, 8, 15, 7, 17, 24"
	},
	"72" : 
	{
		"nbEvaluatedPrograms" : 17,
		"nbEvaluatedTeams" : 6,
		"nbExecutionForEachInstr" : 
		{
			"0" : 3,
			"1" : 4,
			"2" : 3,
			"3" : 4,
			"4" : 3,
			"5" : 2
		},
		"traceTeamIds" : "0, 4, 11, 23, 7, 17"
	},
	"73" : 
	{
		"nbEvaluatedPrograms" : 23,
		"nbEvaluatedTeams" : 6,
		"nbExecutionForEachInstr" : 
		{
			"0" : 9,
			"1" : 5,
			"2" : 3,
			"3" : 2,
			"4" : 7,
			"5" : 1
		},
		"traceTeamIds" : "0, 1, 6, 5, 13, 7"
	},
	"74" : 
	{
		"nbEvaluatedPrograms" : 28,
		"nbEvaluatedTeams" : 7,
		"nbExecutionForEachInstr" : 
		{
			"0" : 11,
			"1" : 6,
			"2" : 3,
			"3" : 1,
			"4" : 6,
			"5" : 1
		},
		"traceTeamIds" : "0, 2, 8, 5, 12, 19, 26"
	},
	"75" : 
	{
		"nbEvaluatedPrograms" : 26,
		"nbEvaluatedTeams" : 6,
		"nbExecutionForEachInstr" : 
		{
			"0" : 9,
			"1" : 8,
			"2" : 4,
			"3" : 1,
			"4" : 3,
			"5" : 1
		},
		"traceTeamIds" : "0, 2, 8, 15, 20, 24"
	},
	"76" : 
	{
		"nbEvaluatedPrograms" : 19,
		"nbEvaluatedTeams" : 5,
		"nbExecutionForEachInstr" : 
		{
			"0" : 8,
			"1" : 4,
			"2" : 3,
			"3" : 2,
			"4" : 4,
			"5" : 1
		},
		"traceTeamIds" : "0, 1, 6, 16, 27"
	},
	"77" : 
	{
		"nbEvaluatedPrograms" : 20,
		"nbEvaluatedTeams" : 6,
		"nbExecutionForEachInstr" : 
		{
			"0" : 7,
			"1" : 3,
			"2" : 3,
			"3" : 1,
			"4" : 4,
			"5" : 1
		},
		"traceTeamIds" : "0, 3, 5, 12, 19, 26"
	},
	"78" : 
	{
		"nbEvaluatedPrograms" : 21,
		"nbEvaluatedTeams" : 6,
		"nbExecutionForEachInstr" : 
		{
			"0" : 8,
			"1" : 4,
			"2" : 3,
			"3" : 2,
			"4" : 4,
			"5" : 2
		},
		"traceTeamIds" : "0, 1, 6, 16, 27, 26"
	},
	"79" : 
	{
		"nbEvaluatedPrograms" : 31,
		"nbEvaluatedTeams" : 7,
		"nbExecutionForEachInstr" : 
		{
			"0" : 10,
			"1" : 9,
			"2" : 4,
			"3" : 3,
			"4" : 4,
			"5" : 2
		},
		"traceTeamIds" : "0, 2, 8, 15, 7, 17, 24"
	},
	"8" : 
	{
		"nbEvaluatedPrograms" : 16,
		"nbEvaluatedTeams" : 4,
		"nbExecutionForEachInstr" : 
		{
			"0" : 7,
			"1" : 3,
			"2" : 3,
			"3" : 3,
			"4" : 3,
			"5" : 2
		},
		"traceTeamIds" : "0, 3, 5, 12"
	},
	"80" : 
	{
		"nbEvaluatedPrograms" : 26,
		"nbEvaluatedTeams" : 6,
		"nbExecutionForEachInstr" : 
		{
			"0" : 9,
			"1" : 6,
			"2" : 3,
			"3" : 3,
			"4" : 4,
			"5" : 2
		},
		"traceTeamIds" : "0, 2, 8, 7, 19, 26"
	},
	"81" : 
	{
		"nbEvaluatedPrograms" : 23,
		"nbEvaluatedTeams" : 6,
		"nbExecutionForEachInstr" : 
		{
			"0" : 9,
			"1" : 5,
			"2" : 3,
			"3" : 2,
			"4" : 7,
			"5" : 1
		},
		"traceTeamIds" : "0, 1, 6, 5, 13, 7"
	},
	"82" : 
	{
		"nbEvaluatedPrograms" : 22,
		"nbEvaluatedTeams" : 4,
		"nbExecutionForEachInstr" : 
		{
			"0" : 9,
			"1" : 6,
			"2" : 3,
			"3" : 2,
			"4" : 3,
			"5" : 1
		},
		"traceTeamIds" : "0, 2, 8, 7"
	},
	"83" : 
	{
		"nbEvaluatedPrograms" : 15,
		"nbEvaluatedTeams" : 5,
		"nbExecutionForEachInstr" : 
		{
			"0" : 4,
			"1" : 3,
			"2" : 4,
			"3" : 3,
			"4" : 1,
			"5" : 1
		},
		"traceTeamIds" : "0, 4, 11, 22, 20"
	},
	"84" : 
	{
		"nbEvaluatedPrograms" : 23,
		"nbEvaluatedTeams" : 6,
		"nbExecutionForEachInstr" : 
		{
			"0" : 9,
			"1" : 5,
			"2" : 3,
			"3" : 2,
			"4" : 7,
			"5" : 1
		},
		"traceTeamIds" : "0, 1, 6, 5, 13, 7"
	},
	"85" : 
	{
		"nbEvaluatedPrograms" : 23,
		"nbEvaluatedTeams" : 6,
		"nbExecutionForEachInstr" : 
		{
			"0" : 8,
			"1" : 4,
			"2" : 3,
			"3" : 3,
			"4" : 5,
			"5" : 2
		},
		"traceTeamIds" : "0, 1, 6, 7, 19, 26"
	},
	"86" : 
	{
		"nbEvaluatedPrograms" : 27,
		"nbEvaluatedTeams" : 6,
		"nbExecutionForEachInstr" : 
		{
			"0" : 9,
			"1" : 8,
			"2" : 4,
			"3" : 1,
			"4" : 3,
			"5" : 3
		},
		"traceTeamIds" : "0, 2, 8, 15, 20, 28"
	},
	"87" : 
	{
		"nbEvaluatedPrograms" : 27,
		"nbEvaluatedTeams" : 6,
		"nbExecutionForEachInstr" : 
		{
			"0" : 9,
			"1" : 8,
			"2" : 4,
			"3" : 1,
			"4" : 3,
			"5" : 3
		},
		"traceTeamIds" : "0, 2, 8, 15, 20, 28"
	},
	"88" : 
	{
		"nbEvaluatedPrograms" : 19,
		"nbEvaluatedTeams" : 4,
		"nbExecutionForEachInstr" : 
		{
			"0" : 8,
			"1" : 4,
			"2" : 3,
			"3" : 2,
			"4" : 4,
			"5" : 1
		},
		"traceTeamIds" : "0, 1, 6, 7"
	},
	"89" : 
	{
		"nbEvaluatedPrograms" : 20,
		"nbEvaluatedTeams" : 7,
		"nbExecutionForEachInstr" : 
		{
			"0" : 5,
			"1" : 4,
			"2" : 4,
			"3" : 3,
			"4" : 2,
			"5" : 1,
			"6" : 1
		},
		"traceTeamIds" : "0, 4, 11, 22, 30, 17, 24"
	},
	"9" : 
	{
		"nbEvaluatedPrograms" : 25,
		"nbEvaluatedTeams" : 5,
		"nbExecutionForEachInstr" : 
		{
			"0" : 9,
			"1" : 7,
			"2" : 4,
			"3" : 2,
			"4" : 4,
			"5" : 1
		},
		"traceTeamIds" : "0, 2, 8, 15, 7"
	},
	"90" : 
	{
		"nbEvaluatedPrograms" : 20,
		"nbEvaluatedTeams" : 7,
		"nbExecutionForEachInstr" : 
		{
			"0" : 5,
			"1" : 4,
			"2" : 4,
			"3" : 3,
			"4" : 2,
			"5" : 1,
			"6" : 1
		},
		"traceTeamIds" : "0, 4, 11, 22, 30, 17, 24"
	},
	"91" : 
	{
		"nbEvaluatedPrograms" : 29,
		"nbEvaluatedTeams" : 7,
		"nbExecutionForEachInstr" : 
		{
			"0" : 9,
			"1" : 7,
			"2" : 4,
			"3" : 3,
			"4" : 5,
			"5" : 2
		},
		"traceTeamIds" : "0, 2, 8, 15, 7, 19, 26"
	},
	"92" : 
	{
		"nbEvaluatedPrograms" : 19,
		"nbEvaluatedTeams" : 7,
		"nbExecutionForEachInstr" : 
		{
			"0" : 3,
			"1" : 5,
			"2" : 3,
			"3" : 4,
			"4" : 3,
			"5" : 2
		},
		"traceTeamIds" : "0, 4, 11, 23, 7, 17, 24"
	},
	"93" : 
	{
		"nbEvaluatedPrograms" : 25,
		"nbEvaluatedTeams" : 6,
		"nbExecutionForEachInstr" : 
		{
			"0" : 11,
			"1" : 5,
			"2" : 3,
			"3" : 1,
			"4" : 6,
			"5" : 1
		},
		"traceTeamIds" : "0, 1, 6, 5, 12, 17"
	},
	"94" : 
	{
		"nbEvaluatedPrograms" : 25,
		"nbEvaluatedTeams" : 7,
		"nbExecutionForEachInstr" : 
		{
			"0" : 7,
			"1" : 4,
			"2" : 6,
			"3" : 3,
			"4" : 3,
			"5" : 2
		},
		"traceTeamIds" : "0, 3, 10, 15, 7, 19, 26"
	},
	"95" : 
	{
		"nbEvaluatedPrograms" : 15,
		"nbEvaluatedTeams" : 5,
		"nbExecutionForEachInstr" : 
		{
			"0" : 4,
			"1" : 3,
			"2" : 4,
			"3" : 3,
			"4" : 1,
			"5" : 1
		},
		"traceTeamIds" : "0, 4, 11, 22, 20"
	},
	"96" : 
	{
		"nbEvaluatedPrograms" : 29,
		"nbEvaluatedTeams" : 7,
		"nbExecutionForEachInstr" : 
		{
			"0" : 9,
			"1" : 7,
			"2" : 4,
			"3" : 3,
			"4" : 5,
			"5" : 2
		},
		"traceTeamIds" : "0, 2, 8, 15, 7, 19, 26"
	},
	"97" : 
	{
		"nbEvaluatedPrograms" : 19,
		"nbEvaluatedTeams" : 5,
		"nbExecutionForEachInstr" : 
		{
			"0" : 8,
			"1" : 4,
			"2" : 3,
			"3" : 2,
			"4" : 4,
			"5" : 1
		},
		"traceTeamIds" : "0, 1, 6, 16, 27"
	},
	"98" : 
	{
		"nbEvaluatedPrograms" : 22,
		"nbEvaluatedTeams" : 4,
		"nbExecutionForEachInstr" : 
		{
			"0" : 9,
			"1" : 6,
			"2" : 3,
			"3" : 2,
			"4" : 3,
			"5" : 1
		},
		"traceTeamIds" : "0, 2, 8, 7"
	},
	"99" : 
	{
		"nbEvaluatedPrograms" : 27,
		"nbEvaluatedTeams" : 6,
		"nbExecutionForEachInstr" : 
		{
			"0" : 9,
			"1" : 8,
			"2" : 4,
			"3" : 1,
			"4" : 3,
			"5" : 3
		},
		"traceTeamIds" : "0, 2, 8, 15, 20, 28"
	}
}